{"version":2,"kind":"Article","sha256":"0c56f22baecc4464b61ba727fe940ce63f239c5d4f3852e438badccc1c32a7fb","slug":"foundations.github.basic-git","location":"/foundations/github/basic-git.md","dependencies":[],"frontmatter":{"title":"Basic Version Control with git","content_includes_title":false,"authors":[{"id":"Project Pythia Community","name":"Project Pythia Community"}],"open_access":true,"license":{"content":{"id":"Apache-2.0","url":"https://opensource.org/licenses/Apache-2.0","name":"Apache License 2.0","free":true,"osi":true},"code":{"id":"CC-BY-4.0","url":"https://creativecommons.org/licenses/by/4.0/","name":"Creative Commons Attribution 4.0 International","free":true,"CC":true}},"github":"https://github.com/projectpythia/pythia-foundations","copyright":"2024","affiliations":[{"id":"University at Albany (State University of New York)","name":"University at Albany (State University of New York)"},{"id":"UCAR/NCAR","name":"UCAR/NCAR"}],"abbreviations":{"FOSS":"Free and open-source software","VCS":"Version control system","FTP":"File transfer protocol","TCP":"Transmission Control Protocol"},"numbering":{"title":{"offset":2}},"edit_url":"https://github.com/projectpythia/pythia-foundations/blob/main/foundations/github/basic-git.md","thumbnail":"/build/Git-Logo-2Color-625e036166d7eb25b253d06a63b0b4b2.png","exports":[{"format":"md","filename":"basic-git.md","url":"/build/basic-git-15445cc950042fa61ac0a5322762f7d6.md"}]},"mdast":{"type":"root","children":[{"type":"block","children":[{"type":"image","url":"/build/Git-Logo-2Color-625e036166d7eb25b253d06a63b0b4b2.png","alt":"Git Logo","width":"400px","align":"center","key":"qCKL6XXEz5","urlSource":"../../images/Git-Logo-2Color.png"},{"type":"heading","depth":2,"position":{"start":{"line":8,"column":1},"end":{"line":8,"column":1}},"children":[{"type":"text","value":"Overview:","position":{"start":{"line":8,"column":1},"end":{"line":8,"column":1}},"key":"xw117rKAwS"}],"identifier":"overview","label":"Overview:","html_id":"overview","implicit":true,"key":"SU8PSfpsju"},{"type":"list","ordered":true,"start":1,"spread":false,"position":{"start":{"line":10,"column":1},"end":{"line":14,"column":1}},"children":[{"type":"listItem","spread":true,"position":{"start":{"line":10,"column":1},"end":{"line":10,"column":1}},"children":[{"type":"text","value":"The need for version control","position":{"start":{"line":10,"column":1},"end":{"line":10,"column":1}},"key":"FBy8zKT8Km"}],"key":"Aw6rKfAQXP"},{"type":"listItem","spread":true,"position":{"start":{"line":11,"column":1},"end":{"line":11,"column":1}},"children":[{"type":"text","value":"Basic git usage","position":{"start":{"line":11,"column":1},"end":{"line":11,"column":1}},"key":"y1uNy9ihqq"}],"key":"SIMQjPgnnA"},{"type":"listItem","spread":true,"position":{"start":{"line":12,"column":1},"end":{"line":12,"column":1}},"children":[{"type":"text","value":"Making your first git commit","position":{"start":{"line":12,"column":1},"end":{"line":12,"column":1}},"key":"aBNhgaStfp"}],"key":"H8AgFdnrAn"},{"type":"listItem","spread":true,"position":{"start":{"line":13,"column":1},"end":{"line":14,"column":1}},"children":[{"type":"text","value":"Viewing and comparing across the commit history","position":{"start":{"line":13,"column":1},"end":{"line":13,"column":1}},"key":"agV3a4tbwS"}],"key":"c7u3YYAZwn"}],"key":"vt9GW3FAGH"},{"type":"heading","depth":2,"position":{"start":{"line":15,"column":1},"end":{"line":15,"column":1}},"children":[{"type":"text","value":"Prerequisites","position":{"start":{"line":15,"column":1},"end":{"line":15,"column":1}},"key":"alZt1ruzxK"}],"identifier":"prerequisites","label":"Prerequisites","html_id":"prerequisites","implicit":true,"key":"NVBUGdg8OW"},{"type":"table","position":{"start":{"line":17,"column":1},"end":{"line":23,"column":1}},"children":[{"type":"tableRow","position":{"start":{"line":17,"column":1},"end":{"line":17,"column":1}},"children":[{"type":"tableCell","header":true,"position":{"start":{"line":17,"column":1},"end":{"line":17,"column":1}},"children":[{"type":"text","value":"Concepts","position":{"start":{"line":17,"column":1},"end":{"line":17,"column":1}},"key":"Xej0NFc1ke"}],"key":"SovUN4CLb3"},{"type":"tableCell","header":true,"position":{"start":{"line":17,"column":1},"end":{"line":17,"column":1}},"children":[{"type":"text","value":"Importance","position":{"start":{"line":17,"column":1},"end":{"line":17,"column":1}},"key":"WuPAiTGOR7"}],"key":"g0dBteMHP3"},{"type":"tableCell","header":true,"position":{"start":{"line":17,"column":1},"end":{"line":17,"column":1}},"children":[{"type":"text","value":"Notes","position":{"start":{"line":17,"column":1},"end":{"line":17,"column":1}},"key":"xtOGTwzPVK"}],"key":"auMdrObAAM"}],"key":"AbrX5hvQEO"},{"type":"tableRow","position":{"start":{"line":19,"column":1},"end":{"line":19,"column":1}},"children":[{"type":"tableCell","position":{"start":{"line":19,"column":1},"end":{"line":19,"column":1}},"children":[{"type":"crossReference","position":{"start":{"line":19,"column":1},"end":{"line":19,"column":1}},"children":[{"type":"text","value":"What is GitHub?","position":{"start":{"line":19,"column":1},"end":{"line":19,"column":1}},"key":"WbNNATD1iD"}],"identifier":"what-is-github","label":"what-is-github","kind":"heading","template":"{name}","resolved":true,"html_id":"what-is-github","remote":true,"url":"/foundations/github/what-is-github","dataUrl":"/foundations.github.what-is-github.json","key":"sjz13kYRKK"}],"key":"z8cSxn0LlU"},{"type":"tableCell","position":{"start":{"line":19,"column":1},"end":{"line":19,"column":1}},"children":[{"type":"text","value":"Necessary","position":{"start":{"line":19,"column":1},"end":{"line":19,"column":1}},"key":"Tlw4PCzrre"}],"key":"vXHN4nY7xB"},{"type":"tableCell","position":{"start":{"line":19,"column":1},"end":{"line":19,"column":1}},"children":[{"type":"text","value":"GitHub user account required","position":{"start":{"line":19,"column":1},"end":{"line":19,"column":1}},"key":"MlpmbuP3hu"}],"key":"km3EUTLB9a"}],"key":"sd9c8EzsB8"},{"type":"tableRow","position":{"start":{"line":20,"column":1},"end":{"line":20,"column":1}},"children":[{"type":"tableCell","position":{"start":{"line":20,"column":1},"end":{"line":20,"column":1}},"children":[{"type":"link","url":"/foundations/github/github-repos","position":{"start":{"line":20,"column":1},"end":{"line":20,"column":1}},"children":[{"type":"text","value":"GitHub Repositories","position":{"start":{"line":20,"column":1},"end":{"line":20,"column":1}},"key":"HHXlxDo5R8"}],"urlSource":"github-repos","dataUrl":"/foundations.github.github-repos.json","internal":true,"protocol":"file","key":"o5Eqq6WcvE"}],"key":"IWafkyiOtB"},{"type":"tableCell","position":{"start":{"line":20,"column":1},"end":{"line":20,"column":1}},"children":[{"type":"text","value":"Necessary","position":{"start":{"line":20,"column":1},"end":{"line":20,"column":1}},"key":"jKUUhMPvM7"}],"key":"ZMBi192Ce2"},{"type":"tableCell","position":{"start":{"line":20,"column":1},"end":{"line":20,"column":1}},"children":[],"key":"kMOkgAmQsB"}],"key":"cb8fq9ciY0"},{"type":"tableRow","position":{"start":{"line":21,"column":1},"end":{"line":21,"column":1}},"children":[{"type":"tableCell","position":{"start":{"line":21,"column":1},"end":{"line":21,"column":1}},"children":[{"type":"link","url":"/foundations/github/github-issues","position":{"start":{"line":21,"column":1},"end":{"line":21,"column":1}},"children":[{"type":"text","value":"Issues and Discussions","position":{"start":{"line":21,"column":1},"end":{"line":21,"column":1}},"key":"kmSGcV3LVO"}],"urlSource":"github-issues","dataUrl":"/foundations.github.github-issues.json","internal":true,"protocol":"file","key":"pmV5vs4PXZ"}],"key":"WivqHKhjKO"},{"type":"tableCell","position":{"start":{"line":21,"column":1},"end":{"line":21,"column":1}},"children":[{"type":"text","value":"Recommended","position":{"start":{"line":21,"column":1},"end":{"line":21,"column":1}},"key":"ShPqITAqqL"}],"key":"wKqvNUuAif"},{"type":"tableCell","position":{"start":{"line":21,"column":1},"end":{"line":21,"column":1}},"children":[],"key":"ETJCHtOOid"}],"key":"Z7XH8Wx2to"},{"type":"tableRow","position":{"start":{"line":22,"column":1},"end":{"line":22,"column":1}},"children":[{"type":"tableCell","position":{"start":{"line":22,"column":1},"end":{"line":22,"column":1}},"children":[{"type":"link","url":"/foundations/github/github-cloning-forking","position":{"start":{"line":22,"column":1},"end":{"line":22,"column":1}},"children":[{"type":"text","value":"Cloning and Forking a Repository","position":{"start":{"line":22,"column":1},"end":{"line":22,"column":1}},"key":"FLt2SdgqRq"}],"urlSource":"github-cloning-forking","dataUrl":"/foundations.github.github-cloning-forking.json","internal":true,"protocol":"file","key":"LAGPSvQpG6"}],"key":"YfqPF7xr9p"},{"type":"tableCell","position":{"start":{"line":22,"column":1},"end":{"line":22,"column":1}},"children":[{"type":"text","value":"Recommended","position":{"start":{"line":22,"column":1},"end":{"line":22,"column":1}},"key":"VtR1f8dR7O"}],"key":"zzCpig8Lha"},{"type":"tableCell","position":{"start":{"line":22,"column":1},"end":{"line":22,"column":1}},"children":[],"key":"C7qOfjVz3d"}],"key":"uM9hT4F7Bi"},{"type":"tableRow","position":{"start":{"line":23,"column":1},"end":{"line":23,"column":1}},"children":[{"type":"tableCell","position":{"start":{"line":23,"column":1},"end":{"line":23,"column":1}},"children":[{"type":"link","url":"/foundations/github/github-setup-advanced","position":{"start":{"line":23,"column":1},"end":{"line":23,"column":1}},"children":[{"type":"text","value":"Configuring your GitHub Account","position":{"start":{"line":23,"column":1},"end":{"line":23,"column":1}},"key":"lB4kkFfYSy"}],"urlSource":"github-setup-advanced","dataUrl":"/foundations.github.github-setup-advanced.json","internal":true,"protocol":"file","key":"u2IVdsEAaO"}],"key":"qpxrxzwa6O"},{"type":"tableCell","position":{"start":{"line":23,"column":1},"end":{"line":23,"column":1}},"children":[{"type":"text","value":"Recommended","position":{"start":{"line":23,"column":1},"end":{"line":23,"column":1}},"key":"P1gEjo7wg1"}],"key":"zJHH76St4c"},{"type":"tableCell","position":{"start":{"line":23,"column":1},"end":{"line":23,"column":1}},"children":[],"key":"jKNToQGN74"}],"key":"T71hZrBMPP"}],"key":"oTMEsCAXSR"},{"type":"list","ordered":false,"spread":false,"position":{"start":{"line":25,"column":1},"end":{"line":26,"column":1}},"children":[{"type":"listItem","spread":true,"position":{"start":{"line":25,"column":1},"end":{"line":26,"column":1}},"children":[{"type":"strong","position":{"start":{"line":25,"column":1},"end":{"line":25,"column":1}},"children":[{"type":"text","value":"Time to learn","position":{"start":{"line":25,"column":1},"end":{"line":25,"column":1}},"key":"Es0O878jUZ"}],"key":"mjXOou8qAa"},{"type":"text","value":": 45 minutes","position":{"start":{"line":25,"column":1},"end":{"line":25,"column":1}},"key":"ZcCQS7B9oD"}],"key":"kytID77MVX"}],"key":"p5H7S91LuM"},{"type":"thematicBreak","position":{"start":{"line":27,"column":1},"end":{"line":27,"column":1}},"key":"qHKp05IuMx"},{"type":"heading","depth":2,"position":{"start":{"line":29,"column":1},"end":{"line":29,"column":1}},"children":[{"type":"text","value":"About version control and git","position":{"start":{"line":29,"column":1},"end":{"line":29,"column":1}},"key":"xcGuVSqxIP"}],"identifier":"about-version-control-and-git","label":"About version control and git","html_id":"about-version-control-and-git","implicit":true,"key":"A0f10NYqCl"},{"type":"heading","depth":3,"position":{"start":{"line":31,"column":1},"end":{"line":31,"column":1}},"children":[{"type":"text","value":"What is version control (and why should we care)?","position":{"start":{"line":31,"column":1},"end":{"line":31,"column":1}},"key":"xXX4TSa5Gv"}],"identifier":"what-is-version-control-and-why-should-we-care","label":"What is version control (and why should we care)?","html_id":"what-is-version-control-and-why-should-we-care","implicit":true,"key":"JTZsRIEOxG"},{"type":"paragraph","position":{"start":{"line":33,"column":1},"end":{"line":33,"column":1}},"children":[{"type":"link","url":"https://en.wikipedia.org/wiki/Version_control","position":{"start":{"line":33,"column":1},"end":{"line":33,"column":1}},"children":[{"type":"text","value":"Version Control","position":{"start":{"line":33,"column":1},"end":{"line":33,"column":1}},"key":"HyuPitBrjz"}],"urlSource":"https://en.wikipedia.org/wiki/Version_control","data":{"page":"Version_control","wiki":"https://en.wikipedia.org/","lang":"en"},"internal":false,"protocol":"wiki","key":"HVlMjVBrkg"},{"type":"text","value":" refers generally to systems for managing changes to documents or files. Version control systems let us keep track of what changes were made to a file, when they were made, and by whom. If you’ve ever used “Tracked changes” on a Word document with multiple authors, then you’ve seen a form of version control in action (though NOT one that is well suited to working with computer code!).","position":{"start":{"line":33,"column":1},"end":{"line":33,"column":1}},"key":"RtxDJAhNRv"}],"key":"dtuYEnAUBj"},{"type":"paragraph","position":{"start":{"line":35,"column":1},"end":{"line":35,"column":1}},"children":[{"type":"text","value":"The need for version control is particularly acute when ","position":{"start":{"line":35,"column":1},"end":{"line":35,"column":1}},"key":"F32HmmiwoW"},{"type":"emphasis","position":{"start":{"line":35,"column":1},"end":{"line":35,"column":1}},"children":[{"type":"text","value":"working with computer code","position":{"start":{"line":35,"column":1},"end":{"line":35,"column":1}},"key":"qRixKbjTgy"}],"key":"T8DGo8gUgi"},{"type":"text","value":", where small changes to the text can have huge impacts on the results of running the code.","position":{"start":{"line":35,"column":1},"end":{"line":35,"column":1}},"key":"hJl4Awp2vL"}],"key":"D8OwzPqdbV"},{"type":"paragraph","position":{"start":{"line":37,"column":1},"end":{"line":37,"column":1}},"children":[{"type":"text","value":"Do you have a directory somewhere on your machine right now with five different versions of a Python script like this?","position":{"start":{"line":37,"column":1},"end":{"line":37,"column":1}},"key":"mwsUhEEkU5"}],"key":"AYrOjt3QOJ"},{"type":"code","lang":"","value":"analysis_script_OLD.py\nanalysis_script.py\nanalysis_script_09122021.py\nanalysis_script_09122021_edit.py\nanalysis_script_NEW.py","position":{"start":{"line":39,"column":1},"end":{"line":45,"column":1}},"key":"TUNyyqR8fO"},{"type":"paragraph","position":{"start":{"line":47,"column":1},"end":{"line":47,"column":1}},"children":[{"type":"text","value":"A Version Control System (","key":"op9y4VLo7F"},{"type":"abbreviation","title":"Version control system","children":[{"type":"text","value":"VCS","key":"qjcuO90WUc"}],"key":"CwGgAwXQsT"},{"type":"text","value":") like git will replace this mess with a ","key":"hPjqA0LGfp"},{"type":"emphasis","position":{"start":{"line":47,"column":1},"end":{"line":47,"column":1}},"children":[{"type":"text","value":"well-ordered and labelled history","position":{"start":{"line":47,"column":1},"end":{"line":47,"column":1}},"key":"KXtrwKRgDm"}],"key":"pI6ClxLwiM"},{"type":"text","value":" of edits that you can freely browse through, and will greatly simplify collaborating with other people on writing new code.","position":{"start":{"line":47,"column":1},"end":{"line":47,"column":1}},"key":"TpjeIm8G5A"}],"key":"mBNc2GIdVf"},{"type":"heading","depth":3,"position":{"start":{"line":49,"column":1},"end":{"line":49,"column":1}},"children":[{"type":"text","value":"What is git?","position":{"start":{"line":49,"column":1},"end":{"line":49,"column":1}},"key":"bEGTdDsG1h"}],"identifier":"what-is-git","label":"What is git?","html_id":"what-is-git","implicit":true,"key":"FS1B2jEHhA"},{"type":"heading","depth":4,"position":{"start":{"line":51,"column":1},"end":{"line":51,"column":1}},"children":[{"type":"text","value":"Git is not GitHub","position":{"start":{"line":51,"column":1},"end":{"line":51,"column":1}},"key":"ypCU2emELk"}],"identifier":"git-is-not-github","label":"Git is not GitHub","html_id":"git-is-not-github","implicit":true,"key":"EFFAnPh27v"},{"type":"paragraph","position":{"start":{"line":53,"column":1},"end":{"line":53,"column":1}},"children":[{"type":"text","value":"That’s the first thing to understand. GitHub is a web-based platform for hosting code and collaborating with other people. On the other hand, ","position":{"start":{"line":53,"column":1},"end":{"line":53,"column":1}},"key":"pRuYxefL6Z"},{"type":"strong","position":{"start":{"line":53,"column":1},"end":{"line":53,"column":1}},"children":[{"type":"text","value":"git is a command-line Version Control System (","key":"FWCiGmGTpf"},{"type":"abbreviation","title":"Version control system","children":[{"type":"text","value":"VCS","key":"CXnCBgl9Ah"}],"key":"hTqRkDwspw"},{"type":"text","value":")","key":"uE4SAUBiyZ"}],"key":"cAOR4hR9T9"},{"type":"text","value":" that you can download and install. It runs on your local computer as well as under the hood on GitHub. You need to understand something about version control with git in order to use many of GitHub’s collaboration features.","position":{"start":{"line":53,"column":1},"end":{"line":53,"column":1}},"key":"JOfrWmRLjN"}],"key":"AHly4kohua"},{"type":"heading","depth":4,"position":{"start":{"line":55,"column":1},"end":{"line":55,"column":1}},"children":[{"type":"text","value":"A little history and nomenclature","position":{"start":{"line":55,"column":1},"end":{"line":55,"column":1}},"key":"VKxjmcr5BT"}],"identifier":"a-little-history-and-nomenclature","label":"A little history and nomenclature","html_id":"a-little-history-and-nomenclature","implicit":true,"key":"Ee0ZSSv3LF"},{"type":"paragraph","position":{"start":{"line":57,"column":1},"end":{"line":57,"column":1}},"children":[{"type":"text","value":"Git has been around ","position":{"start":{"line":57,"column":1},"end":{"line":57,"column":1}},"key":"Onyni7o0IW"},{"type":"link","url":"https://en.wikipedia.org/wiki/Git","position":{"start":{"line":57,"column":1},"end":{"line":57,"column":1}},"children":[{"type":"text","value":"since the mid-2000s","position":{"start":{"line":57,"column":1},"end":{"line":57,"column":1}},"key":"cFKpZ1iBTz"}],"urlSource":"https://en.wikipedia.org/wiki/Git","data":{"page":"Git","wiki":"https://en.wikipedia.org/","lang":"en"},"internal":false,"protocol":"wiki","key":"Tpe0dlCCU0"},{"type":"text","value":". It was originally written by Linus Torvalds specifically for use in development of the Linux kernel. Git is ","position":{"start":{"line":57,"column":1},"end":{"line":57,"column":1}},"key":"Z1n6ZNJHyL"},{"type":"link","url":"https://foundations.projectpythia.org/foundations/github/what-is-github.html#free-and-open-source-software-foss","position":{"start":{"line":57,"column":1},"end":{"line":57,"column":1}},"children":[{"type":"text","value":"FOSS","position":{"start":{"line":57,"column":1},"end":{"line":57,"column":1}},"key":"YCtDomAqcm"}],"urlSource":"https://foundations.projectpythia.org/foundations/github/what-is-github.html#free-and-open-source-software-foss","key":"XUPgrJJuqJ"},{"type":"text","value":" and comes pre-installed on many Linux and Mac OS systems.","position":{"start":{"line":57,"column":1},"end":{"line":57,"column":1}},"key":"wJdCRiwPgQ"}],"key":"CnYXnTniCV"},{"type":"paragraph","position":{"start":{"line":59,"column":1},"end":{"line":59,"column":1}},"children":[{"type":"text","value":"There are many other ","key":"rJIi8GQAeX"},{"type":"abbreviation","title":"Version control system","children":[{"type":"text","value":"VCS","key":"RLYe9myHUx"}],"key":"UkhdOFNZXf"},{"type":"text","value":"s out there. A few that you might encounter in scientific codebases include ","key":"uZsSQfUjSp"},{"type":"link","url":"https://subversion.apache.org","position":{"start":{"line":59,"column":1},"end":{"line":59,"column":1}},"children":[{"type":"text","value":"Subversion","position":{"start":{"line":59,"column":1},"end":{"line":59,"column":1}},"key":"IJY7Gar0yW"}],"urlSource":"https://subversion.apache.org","key":"dPAQss3KlH"},{"type":"text","value":", ","position":{"start":{"line":59,"column":1},"end":{"line":59,"column":1}},"key":"Wj63RhyWco"},{"type":"link","url":"https://www.mercurial-scm.org","position":{"start":{"line":59,"column":1},"end":{"line":59,"column":1}},"children":[{"type":"text","value":"Mercurial","position":{"start":{"line":59,"column":1},"end":{"line":59,"column":1}},"key":"Qph1Yw9ekh"}],"urlSource":"https://www.mercurial-scm.org","key":"cYWb38J0iY"},{"type":"text","value":", and ","position":{"start":{"line":59,"column":1},"end":{"line":59,"column":1}},"key":"t2qSgQOYW5"},{"type":"link","url":"https://en.wikipedia.org/wiki/Concurrent_Versions_System","position":{"start":{"line":59,"column":1},"end":{"line":59,"column":1}},"children":[{"type":"text","value":"CVS","position":{"start":{"line":59,"column":1},"end":{"line":59,"column":1}},"key":"chViIX4Fkg"}],"urlSource":"https://en.wikipedia.org/wiki/Concurrent_Versions_System","data":{"page":"Concurrent_Versions_System","wiki":"https://en.wikipedia.org/","lang":"en"},"internal":false,"protocol":"wiki","key":"JN2Il675v1"},{"type":"text","value":". However, git is overwhelmingly the ","key":"gKzq0DTHm4"},{"type":"abbreviation","title":"Version control system","children":[{"type":"text","value":"VCS","key":"Aol4rj72ke"}],"key":"f9umobiz9E"},{"type":"text","value":" of choice for open-source projects in the Scientific Python ecosystem these days (as well as among software developers more generally).","key":"OIK9p63Sai"}],"key":"AzfQBlaENW"},{"type":"paragraph","position":{"start":{"line":61,"column":1},"end":{"line":61,"column":1}},"children":[{"type":"text","value":"There is no universally agreed-upon meaning of the name “git”. From the ","position":{"start":{"line":61,"column":1},"end":{"line":61,"column":1}},"key":"RDoWg9siMM"},{"type":"link","url":"https://github.com/git/git/blob/master/README.md","position":{"start":{"line":61,"column":1},"end":{"line":61,"column":1}},"children":[{"type":"text","value":"git project’s own README file","position":{"start":{"line":61,"column":1},"end":{"line":61,"column":1}},"key":"yIdnX6x7l7"}],"urlSource":"https://github.com/git/git/blob/master/README.md","data":{"kind":"file","org":"git","repo":"git","reference":"master","file":"README.md","raw":"https://raw.githubusercontent.com/git/git/master/README.md"},"internal":false,"protocol":"github","key":"jtyUtD80qk"},{"type":"text","value":":","position":{"start":{"line":61,"column":1},"end":{"line":61,"column":1}},"key":"QXPURbFt5K"}],"key":"HmxAhcFBdw"},{"type":"blockquote","position":{"start":{"line":63,"column":1},"end":{"line":68,"column":1}},"children":[{"type":"paragraph","position":{"start":{"line":63,"column":1},"end":{"line":63,"column":1}},"children":[{"type":"text","value":"The name “git” was given by Linus Torvalds when he wrote the very first version. He described the tool as “the stupid content tracker” and the name as (depending on your mood):","position":{"start":{"line":63,"column":1},"end":{"line":63,"column":1}},"key":"QWv5UZUqNd"}],"key":"CelViMgEyk"},{"type":"list","ordered":false,"spread":false,"position":{"start":{"line":65,"column":1},"end":{"line":68,"column":1}},"children":[{"type":"listItem","spread":true,"position":{"start":{"line":65,"column":1},"end":{"line":65,"column":1}},"children":[{"type":"text","value":"random three-letter combination that is pronounceable, and not actually used by any common UNIX command. The fact that it is a mispronunciation of “get” may or may not be relevant.","position":{"start":{"line":65,"column":1},"end":{"line":65,"column":1}},"key":"VTkhD3J0tu"}],"key":"fr8XE2Ug98"},{"type":"listItem","spread":true,"position":{"start":{"line":66,"column":1},"end":{"line":66,"column":1}},"children":[{"type":"text","value":"stupid. contemptible and despicable. simple. Take your pick from the dictionary of slang.","position":{"start":{"line":66,"column":1},"end":{"line":66,"column":1}},"key":"HwFi9QJDzZ"}],"key":"apAkJAekFs"},{"type":"listItem","spread":true,"position":{"start":{"line":67,"column":1},"end":{"line":67,"column":1}},"children":[{"type":"text","value":"“global information tracker”: you’re in a good mood, and it actually works for you. Angels sing, and a light suddenly fills the room.","position":{"start":{"line":67,"column":1},"end":{"line":67,"column":1}},"key":"T18WY7mfkD"}],"key":"choLk6C5lg"},{"type":"listItem","spread":true,"position":{"start":{"line":68,"column":1},"end":{"line":68,"column":1}},"children":[{"type":"text","value":"“goddamn idiotic truckload of sh*t”: when it breaks","position":{"start":{"line":68,"column":1},"end":{"line":68,"column":1}},"key":"jkawppNSGg"}],"key":"fPYbVa4s0O"}],"key":"g3iN025mm0"}],"key":"ol2OygeIuu"},{"type":"heading","depth":4,"position":{"start":{"line":70,"column":1},"end":{"line":70,"column":1}},"children":[{"type":"text","value":"Git is a distributed ","key":"xXQPp1CB5s"},{"type":"abbreviation","title":"Version control system","children":[{"type":"text","value":"VCS","key":"xkjkd9H6gT"}],"key":"thYHjajelM"}],"identifier":"git-is-a-distributed-vcs","label":"Git is a distributed VCS","html_id":"git-is-a-distributed-vcs","implicit":true,"key":"TGH5PjGukV"},{"type":"paragraph","position":{"start":{"line":72,"column":1},"end":{"line":72,"column":1}},"children":[{"type":"text","value":"Aside from being free and widely deployed, an important distinguishing feature of git is that it is a distributed Version Control System. Essentially this means that every git directory on every computer is a complete independent repository with complete history.","position":{"start":{"line":72,"column":1},"end":{"line":72,"column":1}},"key":"msXi4LFyNI"}],"key":"L0OVFtuwTS"},{"type":"paragraph","position":{"start":{"line":74,"column":1},"end":{"line":74,"column":1}},"children":[{"type":"text","value":"When we cloned the ","position":{"start":{"line":74,"column":1},"end":{"line":74,"column":1}},"key":"J1keb9hQSL"},{"type":"link","url":"https://github.com/ProjectPythia/github-sandbox","position":{"start":{"line":74,"column":1},"end":{"line":74,"column":1}},"children":[{"type":"inlineCode","value":"github-sandbox","position":{"start":{"line":74,"column":1},"end":{"line":74,"column":1}},"key":"vR1kZrvYTZ"}],"urlSource":"https://github.com/ProjectPythia/github-sandbox","error":true,"key":"qJJ3US1UjM"},{"type":"text","value":" repository back in the ","position":{"start":{"line":74,"column":1},"end":{"line":74,"column":1}},"key":"ffLZNeMbBR"},{"type":"link","url":"/foundations/github/github-cloning-forking","position":{"start":{"line":74,"column":1},"end":{"line":74,"column":1}},"children":[{"type":"text","value":"Cloning and Forking","position":{"start":{"line":74,"column":1},"end":{"line":74,"column":1}},"key":"bp0tLk54zu"}],"urlSource":"github-cloning-forking","dataUrl":"/foundations.github.github-cloning-forking.json","internal":true,"protocol":"file","key":"fT7A6Ug96Z"},{"type":"text","value":" section, we not only copied the current repository files but also the entire revision history of the repo.","position":{"start":{"line":74,"column":1},"end":{"line":74,"column":1}},"key":"O9DsTljfTo"}],"key":"aQbzlg0Kzx"},{"type":"paragraph","position":{"start":{"line":76,"column":1},"end":{"line":76,"column":1}},"children":[{"type":"text","value":"In this section we are going to explore basic git usage ","position":{"start":{"line":76,"column":1},"end":{"line":76,"column":1}},"key":"jmQ8pr5RB8"},{"type":"emphasis","position":{"start":{"line":76,"column":1},"end":{"line":76,"column":1}},"children":[{"type":"text","value":"on our local computer","position":{"start":{"line":76,"column":1},"end":{"line":76,"column":1}},"key":"xs7yvSuQ3g"}],"key":"T0YPQfFdWh"},{"type":"text","value":". Nothing that we do here is going to affect other copies of the repositories stored elsewhere. ","position":{"start":{"line":76,"column":1},"end":{"line":76,"column":1}},"key":"evmsOT7Hmf"},{"type":"emphasis","position":{"start":{"line":76,"column":1},"end":{"line":76,"column":1}},"children":[{"type":"text","value":"So don’t worry about breaking anything!","position":{"start":{"line":76,"column":1},"end":{"line":76,"column":1}},"key":"fR31QWimOw"}],"key":"GR9FHPhjjD"}],"key":"kCnz3mZZVG"},{"type":"paragraph","position":{"start":{"line":78,"column":1},"end":{"line":78,"column":1}},"children":[{"type":"text","value":"Later, we will explore how to collaborate on code repositories using GitHub. But in keep in mind the basic idea that ","position":{"start":{"line":78,"column":1},"end":{"line":78,"column":1}},"key":"CU2rr7Y8IM"},{"type":"emphasis","position":{"start":{"line":78,"column":1},"end":{"line":78,"column":1}},"children":[{"type":"text","value":"all git repos are equal and independent","position":{"start":{"line":78,"column":1},"end":{"line":78,"column":1}},"key":"t79bS439YA"}],"key":"Jrhk0cVYS2"},{"type":"text","value":"! You will have separate copies of repos stored on your local machine and in your GitHub organization.","position":{"start":{"line":78,"column":1},"end":{"line":78,"column":1}},"key":"DgVTilo8Do"}],"key":"SzvXkAFoSS"},{"type":"paragraph","position":{"start":{"line":80,"column":1},"end":{"line":80,"column":1}},"children":[{"type":"text","value":"Now that we are oriented, let’s dive into some basic git usage with the ","position":{"start":{"line":80,"column":1},"end":{"line":80,"column":1}},"key":"UV8wM74w5J"},{"type":"link","url":"https://github.com/ProjectPythia/github-sandbox","position":{"start":{"line":80,"column":1},"end":{"line":80,"column":1}},"children":[{"type":"inlineCode","value":"github-sandbox","position":{"start":{"line":80,"column":1},"end":{"line":80,"column":1}},"key":"JKTVw56Vz9"}],"urlSource":"https://github.com/ProjectPythia/github-sandbox","error":true,"key":"NVre8UWqUp"},{"type":"text","value":" repository!","position":{"start":{"line":80,"column":1},"end":{"line":80,"column":1}},"key":"pGNFqbwzBr"}],"key":"xIhhylhRIM"},{"type":"heading","depth":2,"position":{"start":{"line":82,"column":1},"end":{"line":82,"column":1}},"children":[{"type":"text","value":"Inspect a git repository with ","position":{"start":{"line":82,"column":1},"end":{"line":82,"column":1}},"key":"FfKCIjwKv2"},{"type":"inlineCode","value":"git status","position":{"start":{"line":82,"column":1},"end":{"line":82,"column":1}},"key":"gvO8nn9U75"}],"identifier":"inspect-a-git-repository-with-git-status","label":"Inspect a git repository with git status","html_id":"inspect-a-git-repository-with-git-status","implicit":true,"key":"jysMS3wDvb"},{"type":"paragraph","position":{"start":{"line":84,"column":1},"end":{"line":84,"column":1}},"children":[{"type":"text","value":"First, make sure you followed the steps in the ","position":{"start":{"line":84,"column":1},"end":{"line":84,"column":1}},"key":"SrNclfrTOg"},{"type":"link","url":"/foundations/github/github-cloning-forking","position":{"start":{"line":84,"column":1},"end":{"line":84,"column":1}},"children":[{"type":"text","value":"Cloning a repository","position":{"start":{"line":84,"column":1},"end":{"line":84,"column":1}},"key":"X9LtZkaCDf"}],"urlSource":"github-cloning-forking","dataUrl":"/foundations.github.github-cloning-forking.json","internal":true,"protocol":"file","key":"Og9kJKbV5I"},{"type":"text","value":" lesson to make a clone of the ","position":{"start":{"line":84,"column":1},"end":{"line":84,"column":1}},"key":"DcZcGg5NkP"},{"type":"inlineCode","value":"github-sandbox","position":{"start":{"line":84,"column":1},"end":{"line":84,"column":1}},"key":"iVzWwbKDEd"},{"type":"text","value":" repo on your local computer. Navigate to wherever you saved your copy of the repo.","position":{"start":{"line":84,"column":1},"end":{"line":84,"column":1}},"key":"y5d46zUHSA"}],"key":"aSdxzjIsAl"},{"type":"paragraph","position":{"start":{"line":86,"column":1},"end":{"line":86,"column":1}},"children":[{"type":"text","value":"Now meet your new best friend:","position":{"start":{"line":86,"column":1},"end":{"line":86,"column":1}},"key":"kmAv5p5j9i"}],"key":"kOVqVHx6xO"},{"type":"code","lang":"bash","value":"git status","position":{"start":{"line":88,"column":1},"end":{"line":90,"column":1}},"key":"OrUvldEmDA"},{"type":"paragraph","position":{"start":{"line":92,"column":1},"end":{"line":92,"column":1}},"children":[{"type":"text","value":"which will always give you information about the current git repo. Try it! You should see something like this:","position":{"start":{"line":92,"column":1},"end":{"line":92,"column":1}},"key":"a0SRYFftQO"}],"key":"Tgeonqjzwm"},{"type":"code","lang":"bash","value":"On branch main\nYour branch is up to date with 'origin/main'.\n\nnothing to commit, working tree clean","position":{"start":{"line":94,"column":1},"end":{"line":99,"column":1}},"key":"pBRengCKfP"},{"type":"paragraph","position":{"start":{"line":101,"column":1},"end":{"line":101,"column":1}},"children":[{"type":"strong","position":{"start":{"line":101,"column":1},"end":{"line":101,"column":1}},"children":[{"type":"text","value":"Two really important things here","position":{"start":{"line":101,"column":1},"end":{"line":101,"column":1}},"key":"HldSFXadPF"}],"key":"eEXrx6umnp"},{"type":"text","value":":","position":{"start":{"line":101,"column":1},"end":{"line":101,"column":1}},"key":"dwIk40e8ST"}],"key":"jR39B3EUPe"},{"type":"list","ordered":true,"start":1,"spread":false,"position":{"start":{"line":103,"column":1},"end":{"line":105,"column":1}},"children":[{"type":"listItem","spread":true,"position":{"start":{"line":103,"column":1},"end":{"line":103,"column":1}},"children":[{"type":"text","value":"The first line show you the current ","position":{"start":{"line":103,"column":1},"end":{"line":103,"column":1}},"key":"DTUF5wL6gf"},{"type":"emphasis","position":{"start":{"line":103,"column":1},"end":{"line":103,"column":1}},"children":[{"type":"text","value":"branch","position":{"start":{"line":103,"column":1},"end":{"line":103,"column":1}},"key":"hYsjxoqESB"}],"key":"JiTUBbPsx4"},{"type":"text","value":" (here called ","position":{"start":{"line":103,"column":1},"end":{"line":103,"column":1}},"key":"d3rm3tr4uB"},{"type":"inlineCode","value":"main","position":{"start":{"line":103,"column":1},"end":{"line":103,"column":1}},"key":"Lq2CpVHbMJ"},{"type":"text","value":"). We’ll cover branching in more detail in the ","position":{"start":{"line":103,"column":1},"end":{"line":103,"column":1}},"key":"pXve5WSKEm"},{"type":"link","url":"/foundations/github/git-branches","position":{"start":{"line":103,"column":1},"end":{"line":103,"column":1}},"children":[{"type":"text","value":"next lesson","position":{"start":{"line":103,"column":1},"end":{"line":103,"column":1}},"key":"kAJAd1mCdn"}],"urlSource":"git-branches","dataUrl":"/foundations.github.git-branches.json","internal":true,"protocol":"file","key":"cm68tV6RzR"},{"type":"text","value":", but basically each branch is a completely independent version with its own history. When we start making changes to files, we’ll have to pay attention to which branch we’re currently on.","position":{"start":{"line":103,"column":1},"end":{"line":103,"column":1}},"key":"qF2rzfMR9q"}],"key":"b1u4AbyVjK"},{"type":"listItem","spread":true,"position":{"start":{"line":104,"column":1},"end":{"line":105,"column":1}},"children":[{"type":"text","value":"The last line ","position":{"start":{"line":104,"column":1},"end":{"line":104,"column":1}},"key":"OfB4T8IzHm"},{"type":"inlineCode","value":"nothing to commit, working tree clean","position":{"start":{"line":104,"column":1},"end":{"line":104,"column":1}},"key":"xrOJXzHNrL"},{"type":"text","value":" tells us that we haven’t made any changes to files.","position":{"start":{"line":104,"column":1},"end":{"line":104,"column":1}},"key":"j2xU7cBhbZ"}],"key":"YGpha8U3me"}],"key":"NF1To5DuMm"},{"type":"paragraph","position":{"start":{"line":106,"column":1},"end":{"line":106,"column":1}},"children":[{"type":"text","value":"You’ll want to use","position":{"start":{"line":106,"column":1},"end":{"line":106,"column":1}},"key":"yTP9AuA766"}],"key":"UuH2jsljRf"},{"type":"code","lang":"bash","value":"git status","position":{"start":{"line":108,"column":1},"end":{"line":110,"column":1}},"key":"IubZWennUK"},{"type":"paragraph","position":{"start":{"line":112,"column":1},"end":{"line":112,"column":1}},"children":[{"type":"text","value":"frequently to keep track of things in your repos.","position":{"start":{"line":112,"column":1},"end":{"line":112,"column":1}},"key":"Cu2CrgVWs2"}],"key":"Gbj50FTXJq"},{"type":"heading","depth":2,"position":{"start":{"line":114,"column":1},"end":{"line":114,"column":1}},"children":[{"type":"text","value":"Make some changes","position":{"start":{"line":114,"column":1},"end":{"line":114,"column":1}},"key":"G8fSBwMVC5"}],"identifier":"make-some-changes","label":"Make some changes","html_id":"make-some-changes","implicit":true,"key":"X5Bbtr2DLE"},{"type":"paragraph","position":{"start":{"line":116,"column":1},"end":{"line":116,"column":1}},"children":[{"type":"text","value":"Version control is all about keeping track of changes made to files. So let’s make some changes!","position":{"start":{"line":116,"column":1},"end":{"line":116,"column":1}},"key":"ocrYIJ5Grl"}],"key":"Jkp62wA22h"},{"type":"paragraph","position":{"start":{"line":118,"column":1},"end":{"line":118,"column":1}},"children":[{"type":"text","value":"You may have noticed that the file ","position":{"start":{"line":118,"column":1},"end":{"line":118,"column":1}},"key":"kSxE5I9Awc"},{"type":"inlineCode","value":"sample.txt","position":{"start":{"line":118,"column":1},"end":{"line":118,"column":1}},"key":"wgKAtv8fVG"},{"type":"text","value":" in the ","position":{"start":{"line":118,"column":1},"end":{"line":118,"column":1}},"key":"EkAIG6yyhJ"},{"type":"inlineCode","value":"github-sandbox","position":{"start":{"line":118,"column":1},"end":{"line":118,"column":1}},"key":"iM2NVAY1PF"},{"type":"text","value":" repository contains a typo. Here we’re going to fix the error and save it locally.","position":{"start":{"line":118,"column":1},"end":{"line":118,"column":1}},"key":"LUNrZM30fY"}],"key":"ITGcgsV9B5"},{"type":"heading","depth":3,"position":{"start":{"line":120,"column":1},"end":{"line":120,"column":1}},"children":[{"type":"text","value":"Create a new feature branch","position":{"start":{"line":120,"column":1},"end":{"line":120,"column":1}},"key":"Y9ZOMahE6R"}],"identifier":"create-a-new-feature-branch","label":"Create a new feature branch","html_id":"create-a-new-feature-branch","implicit":true,"key":"u1QnJl4s8i"},{"type":"paragraph","position":{"start":{"line":122,"column":1},"end":{"line":122,"column":1}},"children":[{"type":"text","value":"Before we start editing files, the first thing to do is to ","position":{"start":{"line":122,"column":1},"end":{"line":122,"column":1}},"key":"t7XVZFWuwr"},{"type":"emphasis","position":{"start":{"line":122,"column":1},"end":{"line":122,"column":1}},"children":[{"type":"text","value":"create a new branch","position":{"start":{"line":122,"column":1},"end":{"line":122,"column":1}},"key":"bVll69daDt"}],"key":"SLLbW3XjsP"},{"type":"text","value":" where we can safely make any changes we want.","position":{"start":{"line":122,"column":1},"end":{"line":122,"column":1}},"key":"UARFFVTXYN"}],"key":"YKLwRACz6d"},{"type":"admonition","kind":"tip","children":[{"type":"admonitionTitle","children":[{"type":"text","value":"Tip","key":"mqiEpev2KG"}],"key":"DxSqYxqDZp"},{"type":"paragraph","position":{"start":{"line":125,"column":1},"end":{"line":125,"column":1}},"children":[{"type":"text","value":"While there’s nothing stopping us from making changes directly to the ","position":{"start":{"line":125,"column":1},"end":{"line":125,"column":1}},"key":"QasFUN165i"},{"type":"inlineCode","value":"main","position":{"start":{"line":125,"column":1},"end":{"line":125,"column":1}},"key":"Z5MUOP8sWb"},{"type":"text","value":" branch, it’s often best to avoid this! The reason is that it makes collaboration trickier. See the ","position":{"start":{"line":125,"column":1},"end":{"line":125,"column":1}},"key":"zdOwFqUaeI"},{"type":"link","url":"/foundations/github/github-pull-request","position":{"start":{"line":125,"column":1},"end":{"line":125,"column":1}},"children":[{"type":"text","value":"lesson on Pull Requests","position":{"start":{"line":125,"column":1},"end":{"line":125,"column":1}},"key":"O4zST6PBkY"}],"urlSource":"github-pull-request","dataUrl":"/foundations.github.github-pull-request.json","internal":true,"protocol":"file","key":"qyIthfFBVf"},{"type":"text","value":".","position":{"start":{"line":125,"column":1},"end":{"line":125,"column":1}},"key":"yU7KOhC0QC"}],"key":"MA2rkDsOgf"}],"key":"Wlqq9nSAIx"},{"type":"paragraph","position":{"start":{"line":128,"column":1},"end":{"line":128,"column":1}},"children":[{"type":"text","value":"Let’s create and checkout a new branch in one line:","position":{"start":{"line":128,"column":1},"end":{"line":128,"column":1}},"key":"QDTy1UJ6Nh"}],"key":"ccnbdg6KD1"},{"type":"code","lang":"bash","value":"git checkout -b fix-typo","position":{"start":{"line":130,"column":1},"end":{"line":132,"column":1}},"key":"EzT1epjdRH"},{"type":"paragraph","position":{"start":{"line":134,"column":1},"end":{"line":134,"column":1}},"children":[{"type":"text","value":"Now try your new best friend again:","position":{"start":{"line":134,"column":1},"end":{"line":134,"column":1}},"key":"snwV84pwtr"}],"key":"dd6Z8yPklW"},{"type":"code","lang":"bash","value":"git status","position":{"start":{"line":136,"column":1},"end":{"line":138,"column":1}},"key":"s8fWMWgDZs"},{"type":"paragraph","position":{"start":{"line":140,"column":1},"end":{"line":140,"column":1}},"children":[{"type":"text","value":"You should see something like this:","position":{"start":{"line":140,"column":1},"end":{"line":140,"column":1}},"key":"XfXiiFp95w"}],"key":"UAlopCk4D5"},{"type":"code","lang":"bash","value":"On branch fix-typo\nnothing to commit, working tree clean","position":{"start":{"line":142,"column":1},"end":{"line":145,"column":1}},"key":"PnlcLbiSYX"},{"type":"paragraph","position":{"start":{"line":147,"column":1},"end":{"line":147,"column":1}},"children":[{"type":"text","value":"This tells us that we have switched over to a new branch called ","position":{"start":{"line":147,"column":1},"end":{"line":147,"column":1}},"key":"Zjzkvz0dEe"},{"type":"inlineCode","value":"fix-typo","position":{"start":{"line":147,"column":1},"end":{"line":147,"column":1}},"key":"xBjDsZSgKS"},{"type":"text","value":", but there are not (yet) any changes to the files in the repo.","position":{"start":{"line":147,"column":1},"end":{"line":147,"column":1}},"key":"mHbK4pLlg9"}],"key":"hPZ6SOjH6Z"},{"type":"heading","depth":3,"position":{"start":{"line":149,"column":1},"end":{"line":149,"column":1}},"children":[{"type":"text","value":"Time to make some changes","position":{"start":{"line":149,"column":1},"end":{"line":149,"column":1}},"key":"i7p6SzHoBV"}],"identifier":"time-to-make-some-changes","label":"Time to make some changes","html_id":"time-to-make-some-changes","implicit":true,"key":"oCvxzWvqlq"},{"type":"paragraph","position":{"start":{"line":151,"column":1},"end":{"line":151,"column":1}},"children":[{"type":"text","value":"Now do the following:","position":{"start":{"line":151,"column":1},"end":{"line":151,"column":1}},"key":"TaHfVUuCoZ"}],"key":"dsKJxiUHMJ"},{"type":"list","ordered":false,"spread":false,"position":{"start":{"line":153,"column":1},"end":{"line":157,"column":1}},"children":[{"type":"listItem","spread":true,"position":{"start":{"line":153,"column":1},"end":{"line":153,"column":1}},"children":[{"type":"text","value":"Using your favorite text editor, open the file ","position":{"start":{"line":153,"column":1},"end":{"line":153,"column":1}},"key":"W95ExwxhUf"},{"type":"inlineCode","value":"github-sandbox/sample.txt","position":{"start":{"line":153,"column":1},"end":{"line":153,"column":1}},"key":"mtGw1Etd2I"},{"type":"text","value":".","position":{"start":{"line":153,"column":1},"end":{"line":153,"column":1}},"key":"kFml9swC7n"}],"key":"XSHjYUON81"},{"type":"listItem","spread":true,"position":{"start":{"line":154,"column":1},"end":{"line":154,"column":1}},"children":[{"type":"text","value":"Replace the word ","position":{"start":{"line":154,"column":1},"end":{"line":154,"column":1}},"key":"dQKgFBHjh4"},{"type":"inlineCode","value":"Fxing","position":{"start":{"line":154,"column":1},"end":{"line":154,"column":1}},"key":"zcLrmJzCki"},{"type":"text","value":" with the much more satisfying ","position":{"start":{"line":154,"column":1},"end":{"line":154,"column":1}},"key":"O8w3eDz0EW"},{"type":"inlineCode","value":"Fixing","position":{"start":{"line":154,"column":1},"end":{"line":154,"column":1}},"key":"Z7S5x2aqir"},{"type":"text","value":".","position":{"start":{"line":154,"column":1},"end":{"line":154,"column":1}},"key":"QiwoidHJVf"}],"key":"vOffVIiRWc"},{"type":"listItem","spread":true,"position":{"start":{"line":155,"column":1},"end":{"line":155,"column":1}},"children":[{"type":"text","value":"Save the changes.","position":{"start":{"line":155,"column":1},"end":{"line":155,"column":1}},"key":"ZjVdUxl3Il"}],"key":"U91DxfeKEH"},{"type":"listItem","spread":true,"position":{"start":{"line":156,"column":1},"end":{"line":157,"column":1}},"children":[{"type":"text","value":"Revisit your new best friend ","position":{"start":{"line":156,"column":1},"end":{"line":156,"column":1}},"key":"j9KYqoIZ4B"},{"type":"inlineCode","value":"git status","position":{"start":{"line":156,"column":1},"end":{"line":156,"column":1}},"key":"gyY7YMCH0x"},{"type":"text","value":". It should now show something like this:","position":{"start":{"line":156,"column":1},"end":{"line":156,"column":1}},"key":"XBh1ed0o5X"}],"key":"yqOoESU3Ik"}],"key":"tHvMlQE2fH"},{"type":"code","lang":"bash","value":"On branch fix-typo\nChanges not staged for commit:\n  (use \"git add <file>...\" to update what will be committed)\n  (use \"git restore <file>...\" to discard changes in working directory)\n\tmodified:   sample.txt\n\nno changes added to commit (use \"git add\" and/or \"git commit -a\")","position":{"start":{"line":158,"column":1},"end":{"line":166,"column":1}},"key":"JsKmPjRszg"},{"type":"paragraph","position":{"start":{"line":168,"column":1},"end":{"line":168,"column":1}},"children":[{"type":"text","value":"Here ","position":{"start":{"line":168,"column":1},"end":{"line":168,"column":1}},"key":"L4DurONv9n"},{"type":"inlineCode","value":"git","position":{"start":{"line":168,"column":1},"end":{"line":168,"column":1}},"key":"zyxR8rCxuF"},{"type":"text","value":" is telling us that the file ","position":{"start":{"line":168,"column":1},"end":{"line":168,"column":1}},"key":"ctwcwJKcMr"},{"type":"inlineCode","value":"sample.txt","position":{"start":{"line":168,"column":1},"end":{"line":168,"column":1}},"key":"vxwJoFWycB"},{"type":"text","value":" does ","position":{"start":{"line":168,"column":1},"end":{"line":168,"column":1}},"key":"wU96IwXghO"},{"type":"emphasis","position":{"start":{"line":168,"column":1},"end":{"line":168,"column":1}},"children":[{"type":"text","value":"not","position":{"start":{"line":168,"column":1},"end":{"line":168,"column":1}},"key":"rf2fKHnMi8"}],"key":"mpyxUG0DCk"},{"type":"text","value":" match what’s in the repository.","position":{"start":{"line":168,"column":1},"end":{"line":168,"column":1}},"key":"QpDL5xWYzz"}],"key":"LZcsZvcO4K"},{"type":"paragraph","position":{"start":{"line":170,"column":1},"end":{"line":170,"column":1}},"children":[{"type":"text","value":"Of course we know what changed in that file because we just finished editing it. But here’s a quick and easy way to see the changes:","position":{"start":{"line":170,"column":1},"end":{"line":170,"column":1}},"key":"N5FsoGWRDh"}],"key":"Z1im3F2oSG"},{"type":"code","lang":"bash","value":"git diff","position":{"start":{"line":172,"column":1},"end":{"line":174,"column":1}},"key":"BBA0o67EvI"},{"type":"paragraph","position":{"start":{"line":176,"column":1},"end":{"line":176,"column":1}},"children":[{"type":"text","value":"which should show you something like this:","position":{"start":{"line":176,"column":1},"end":{"line":176,"column":1}},"key":"JeIojnLQYy"}],"key":"vevIPJa5R6"},{"type":"code","lang":"bash","value":"diff --git a/sample.txt b/sample.txt\nindex 4bc074c..edc31c0 100644\n--- a/sample.txt\n+++ b/sample.txt\n@@ -4,6 +4,6 @@ We can use it to demonstrate making pull requests or raising issues in a GitHub\n\n One good way to contribute to a project is to make additions and/or edits to documentation!\n\n-Fxing something as simple as a typo is a great way to get started as a contributor!\n+Fixing something as simple as a typo is a great way to get started as a contributor!\n\n Or, consider adding some more content to this file.","position":{"start":{"line":178,"column":1},"end":{"line":191,"column":1}},"key":"lcPUTx1jlf"},{"type":"paragraph","position":{"start":{"line":193,"column":1},"end":{"line":193,"column":1}},"children":[{"type":"text","value":"We can see here that ","position":{"start":{"line":193,"column":1},"end":{"line":193,"column":1}},"key":"kXYrYwI9ZG"},{"type":"inlineCode","value":"git diff","position":{"start":{"line":193,"column":1},"end":{"line":193,"column":1}},"key":"VzQ9WINGZ2"},{"type":"text","value":" finds the line(s) where our current file differs from what’s in the repo, along with a few lines before and after for context.","position":{"start":{"line":193,"column":1},"end":{"line":193,"column":1}},"key":"l9RiwNnL7P"}],"key":"rXGoBLXZq3"},{"type":"paragraph","position":{"start":{"line":195,"column":1},"end":{"line":195,"column":1}},"children":[{"type":"text","value":"The next step is to add our changes to the “official” history of our repo. This is a two-step process (staging and committing).","position":{"start":{"line":195,"column":1},"end":{"line":195,"column":1}},"key":"Is7s5Z7qZ5"}],"key":"wcg5NrabSZ"},{"type":"heading","depth":2,"position":{"start":{"line":197,"column":1},"end":{"line":197,"column":1}},"children":[{"type":"text","value":"Stage and commit our changes","position":{"start":{"line":197,"column":1},"end":{"line":197,"column":1}},"key":"NHeH8BMWAd"}],"identifier":"stage-and-commit-our-changes","label":"Stage and commit our changes","html_id":"stage-and-commit-our-changes","implicit":true,"key":"JzBdL2iFdt"},{"type":"paragraph","position":{"start":{"line":199,"column":1},"end":{"line":199,"column":1}},"children":[{"type":"text","value":"The ","position":{"start":{"line":199,"column":1},"end":{"line":199,"column":1}},"key":"eHOjfI3T8m"},{"type":"inlineCode","value":"commit","position":{"start":{"line":199,"column":1},"end":{"line":199,"column":1}},"key":"ux4XYDVQzl"},{"type":"text","value":" is the centerpiece of the git workflow. Each commit is a specific set of changes, additions, and/or deletions of files that gets added to the official history of the repository.","position":{"start":{"line":199,"column":1},"end":{"line":199,"column":1}},"key":"u4rvJ9Tbam"}],"key":"Au9HNf3ORc"},{"type":"heading","depth":3,"position":{"start":{"line":201,"column":1},"end":{"line":201,"column":1}},"children":[{"type":"text","value":"Staging","position":{"start":{"line":201,"column":1},"end":{"line":201,"column":1}},"key":"d37laPP5cG"}],"identifier":"staging","label":"Staging","html_id":"staging","implicit":true,"key":"Ri5QjPMxog"},{"type":"paragraph","position":{"start":{"line":203,"column":1},"end":{"line":203,"column":1}},"children":[{"type":"text","value":"Before we make a commit, we must first stage our changes. Think of staging simply as “getting ready to commit”. The two-step process can help avoid accidentally committing something that wasn’t ready.","position":{"start":{"line":203,"column":1},"end":{"line":203,"column":1}},"key":"Duvn9Lkziq"}],"key":"FosptGK6NI"},{"type":"paragraph","position":{"start":{"line":205,"column":1},"end":{"line":205,"column":1}},"children":[{"type":"text","value":"To stage our changes, we use ","position":{"start":{"line":205,"column":1},"end":{"line":205,"column":1}},"key":"sWdDE1jwyA"},{"type":"inlineCode","value":"git add","position":{"start":{"line":205,"column":1},"end":{"line":205,"column":1}},"key":"oUwSwaZw2B"},{"type":"text","value":" like this:","position":{"start":{"line":205,"column":1},"end":{"line":205,"column":1}},"key":"rUYfMl40rT"}],"key":"pk4w2RGSXa"},{"type":"code","lang":"bash","value":"git add sample.txt","position":{"start":{"line":207,"column":1},"end":{"line":209,"column":1}},"key":"SD2H9B3uCJ"},{"type":"paragraph","position":{"start":{"line":211,"column":1},"end":{"line":211,"column":1}},"children":[{"type":"text","value":"and now our new best friend tells us","position":{"start":{"line":211,"column":1},"end":{"line":211,"column":1}},"key":"s0QtAkFtHq"}],"key":"Nbkb5keRzS"},{"type":"code","lang":"bash","value":"On branch fix-typo\nChanges to be committed:\n  (use \"git restore --staged <file>...\" to unstage)\n\tmodified:   sample.txt\n","position":{"start":{"line":213,"column":1},"end":{"line":219,"column":1}},"key":"i6by3GULng"},{"type":"paragraph","position":{"start":{"line":221,"column":1},"end":{"line":221,"column":1}},"children":[{"type":"text","value":"Now we see that all-important line ","position":{"start":{"line":221,"column":1},"end":{"line":221,"column":1}},"key":"ck6wJuw0cB"},{"type":"inlineCode","value":"Changes to be committed","position":{"start":{"line":221,"column":1},"end":{"line":221,"column":1}},"key":"wJK743tbfT"},{"type":"text","value":", telling us the contents of our staging area.","position":{"start":{"line":221,"column":1},"end":{"line":221,"column":1}},"key":"BZs0mQNPef"}],"key":"WvlEfHEugn"},{"type":"paragraph","position":{"start":{"line":223,"column":1},"end":{"line":223,"column":1}},"children":[{"type":"text","value":"If you made a mistake (e.g., staged the wrong file), you can always unstage using ","position":{"start":{"line":223,"column":1},"end":{"line":223,"column":1}},"key":"wSJyj50fRN"},{"type":"inlineCode","value":"git restore","position":{"start":{"line":223,"column":1},"end":{"line":223,"column":1}},"key":"PFKybZbCdW"},{"type":"text","value":" as shown in the ","position":{"start":{"line":223,"column":1},"end":{"line":223,"column":1}},"key":"AAY34DkqMQ"},{"type":"inlineCode","value":"git status","position":{"start":{"line":223,"column":1},"end":{"line":223,"column":1}},"key":"dOBPB5QRUc"},{"type":"text","value":" output. Nothing is permanent until we commit!","position":{"start":{"line":223,"column":1},"end":{"line":223,"column":1}},"key":"CUgOXd9LXi"}],"key":"bhlw7AgcLB"},{"type":"paragraph","position":{"start":{"line":225,"column":1},"end":{"line":225,"column":1}},"children":[{"type":"text","value":"(And if you accidentally commit the wrong thing? Don’t worry, you can always “go back in time” to previous commits -- see below!)","position":{"start":{"line":225,"column":1},"end":{"line":225,"column":1}},"key":"Xn4agcQbRU"}],"key":"LywSqgoT2G"},{"type":"heading","depth":3,"position":{"start":{"line":227,"column":1},"end":{"line":227,"column":1}},"children":[{"type":"text","value":"Committing","position":{"start":{"line":227,"column":1},"end":{"line":227,"column":1}},"key":"J6eBzgxikW"}],"identifier":"committing","label":"Committing","html_id":"committing","implicit":true,"key":"uZr3kasMk5"},{"type":"paragraph","position":{"start":{"line":229,"column":1},"end":{"line":229,"column":1}},"children":[{"type":"text","value":"It’s time to make a commitment. We can now permanently add our edit to the history of our ","position":{"start":{"line":229,"column":1},"end":{"line":229,"column":1}},"key":"OgjtCv9tWr"},{"type":"inlineCode","value":"fix-typo","position":{"start":{"line":229,"column":1},"end":{"line":229,"column":1}},"key":"VZb4kJNKdX"},{"type":"text","value":" branch by doing this:","position":{"start":{"line":229,"column":1},"end":{"line":229,"column":1}},"key":"EAYEm7j4Wx"}],"key":"KbYvmI7j5M"},{"type":"code","lang":"bash","value":"git commit -m 'Fix the typo'","position":{"start":{"line":231,"column":1},"end":{"line":233,"column":1}},"key":"bnanHmnRPI"},{"type":"admonition","kind":"note","children":[{"type":"admonitionTitle","children":[{"type":"text","value":"Note","key":"kbTnAkAe11"}],"key":"mt4bHTVcwR"},{"type":"paragraph","position":{"start":{"line":236,"column":1},"end":{"line":236,"column":1}},"children":[{"type":"text","value":"Every commit should have a “message” that explains briefly what the commit is for. Here we set the commit message with the ","position":{"start":{"line":236,"column":1},"end":{"line":236,"column":1}},"key":"y0Djcvanb0"},{"type":"inlineCode","value":"-m","position":{"start":{"line":236,"column":1},"end":{"line":236,"column":1}},"key":"Tr7Psc9OfH"},{"type":"text","value":" flag and chose some descriptive text. Note, it’s critical to have those quotes around ","position":{"start":{"line":236,"column":1},"end":{"line":236,"column":1}},"key":"N3tWjVFFcd"},{"type":"inlineCode","value":"'Fix the typo'","position":{"start":{"line":236,"column":1},"end":{"line":236,"column":1}},"key":"E6zUqktlnP"},{"type":"text","value":". Otherwise the command shell will misinterpret what you are trying to do.","position":{"start":{"line":236,"column":1},"end":{"line":236,"column":1}},"key":"ea0kRP3eG4"}],"key":"WNghv0soW3"}],"key":"HoCc6R5130"},{"type":"paragraph","position":{"start":{"line":239,"column":1},"end":{"line":239,"column":1}},"children":[{"type":"text","value":"Now when we do ","position":{"start":{"line":239,"column":1},"end":{"line":239,"column":1}},"key":"AKcS3tMe7D"},{"type":"inlineCode","value":"git status","position":{"start":{"line":239,"column":1},"end":{"line":239,"column":1}},"key":"svYixlpsAl"},{"type":"text","value":" we see","position":{"start":{"line":239,"column":1},"end":{"line":239,"column":1}},"key":"mlXkDkz6oJ"}],"key":"s2oHiw1cVo"},{"type":"code","lang":"bash","value":"On branch fix-typo\nnothing to commit, working tree clean","position":{"start":{"line":241,"column":1},"end":{"line":244,"column":1}},"key":"xhStWbnTuz"},{"type":"paragraph","position":{"start":{"line":246,"column":1},"end":{"line":246,"column":1}},"children":[{"type":"text","value":"And we’re back to a clean state! We have now added a new permanent change to the history of our repo (or more specifically, to this ","position":{"start":{"line":246,"column":1},"end":{"line":246,"column":1}},"key":"Bco6Ng3cZg"},{"type":"emphasis","position":{"start":{"line":246,"column":1},"end":{"line":246,"column":1}},"children":[{"type":"text","value":"branch","position":{"start":{"line":246,"column":1},"end":{"line":246,"column":1}},"key":"tv70schiFc"}],"key":"L6RTTzXIz4"},{"type":"text","value":" of the repo).","position":{"start":{"line":246,"column":1},"end":{"line":246,"column":1}},"key":"H5ztEdAiUS"}],"key":"utJaqaZGWc"},{"type":"heading","depth":2,"position":{"start":{"line":248,"column":1},"end":{"line":248,"column":1}},"children":[{"type":"text","value":"Going back in time","position":{"start":{"line":248,"column":1},"end":{"line":248,"column":1}},"key":"zxYZSBYpV8"}],"identifier":"going-back-in-time","label":"Going back in time","html_id":"going-back-in-time","implicit":true,"key":"IAAppTqBXj"},{"type":"paragraph","position":{"start":{"line":250,"column":1},"end":{"line":250,"column":1}},"children":[{"type":"text","value":"Each commit is essentially a snapshot in time of the state of the repo. So how can we look back on that history, or revert back to a previous version of a file?","position":{"start":{"line":250,"column":1},"end":{"line":250,"column":1}},"key":"DonYTh8zlm"}],"key":"FQzTyA2znY"},{"type":"heading","depth":3,"position":{"start":{"line":252,"column":1},"end":{"line":252,"column":1}},"children":[{"type":"text","value":"Viewing the commit history with ","position":{"start":{"line":252,"column":1},"end":{"line":252,"column":1}},"key":"w4xqGfwUZq"},{"type":"inlineCode","value":"git log","position":{"start":{"line":252,"column":1},"end":{"line":252,"column":1}},"key":"OQMdLMExxN"}],"identifier":"viewing-the-commit-history-with-git-log","label":"Viewing the commit history with git log","html_id":"viewing-the-commit-history-with-git-log","implicit":true,"key":"MsuFbNRGM6"},{"type":"paragraph","position":{"start":{"line":254,"column":1},"end":{"line":254,"column":1}},"children":[{"type":"text","value":"A simple way to see this history of the current branch is this:","position":{"start":{"line":254,"column":1},"end":{"line":254,"column":1}},"key":"RBVVzyBjj6"}],"key":"nAXCENR2Pw"},{"type":"code","lang":"bash","value":"git log","position":{"start":{"line":256,"column":1},"end":{"line":258,"column":1}},"key":"gBjb9FBhJD"},{"type":"paragraph","position":{"start":{"line":260,"column":1},"end":{"line":260,"column":1}},"children":[{"type":"text","value":"You’ll see something like this:","position":{"start":{"line":260,"column":1},"end":{"line":260,"column":1}},"key":"j9XyuDUHMc"}],"key":"n6GDfTkxUy"},{"type":"code","lang":"bash","value":"commit 7dca0292467e4bbd73643556f83fd1c52b5c113c (HEAD -> fix-typo)\nAuthor: Brian Rose <brose@albany.edu>\nDate:   Mon Jan 17 11:31:49 2022 -0500\n\n    Fix the typo\n\ncommit 35fcbd991f911e170df550db58f74a082ba18b50 (origin/main, origin/HEAD, main)\nAuthor: Kevin Tyle <ktyle@albany.edu>\nDate:   Thu Jan 13 11:29:40 2022 -0500\n\n    Close docstring quote on sample.py\n\ncommit e56ea58071f150ec00904a50341a672456cbcb8f\nAuthor: Kevin Tyle <ktyle@albany.edu>\nDate:   Tue Jan 11 14:15:31 2022 -0500\n\n    Create sample.md\n\ncommit f98d05e312d19a84b74c45402a2904ab94d86e45\nAuthor: Kevin Tyle <ktyle@albany.edu>\nDate:   Tue Jan 11 13:58:09 2022 -0500\n\n    Create sample.py","position":{"start":{"line":262,"column":1},"end":{"line":286,"column":1}},"key":"IXJhuRPyzD"},{"type":"paragraph","position":{"start":{"line":288,"column":1},"end":{"line":289,"column":1}},"children":[{"type":"text","value":"which shows the last few commits on this branch, including the commit number, author, timestamp, and commit message. You can page down to see the rest of the history\nor just press ","position":{"start":{"line":288,"column":1},"end":{"line":288,"column":1}},"key":"ezRYAn88fN"},{"type":"inlineCode","value":"Q","position":{"start":{"line":288,"column":1},"end":{"line":288,"column":1}},"key":"fBE9qYp7K9"},{"type":"text","value":" to exit ","position":{"start":{"line":288,"column":1},"end":{"line":288,"column":1}},"key":"f7Njmz64KT"},{"type":"inlineCode","value":"git log","position":{"start":{"line":288,"column":1},"end":{"line":288,"column":1}},"key":"qMxJX4RN5e"},{"type":"text","value":"!","position":{"start":{"line":288,"column":1},"end":{"line":288,"column":1}},"key":"IYrvtjtUoI"}],"key":"LW8z6aH0CQ"},{"type":"admonition","kind":"note","children":[{"type":"admonitionTitle","children":[{"type":"text","value":"Note","key":"S9Hk7lQUwr"}],"key":"PcVe71mWUX"},{"type":"paragraph","position":{"start":{"line":292,"column":1},"end":{"line":292,"column":1}},"children":[{"type":"text","value":"Every commit has a unique hexadecimal checksum code like ","position":{"start":{"line":292,"column":1},"end":{"line":292,"column":1}},"key":"bZgbsZ7opB"},{"type":"inlineCode","value":"7dca0292467e4bbd73643556f83fd1c52b5c113c","position":{"start":{"line":292,"column":1},"end":{"line":292,"column":1}},"key":"UgTZJucgN8"},{"type":"text","value":". Your history will look a little different from the above!","position":{"start":{"line":292,"column":1},"end":{"line":292,"column":1}},"key":"Q51pf36EaF"}],"key":"BEEco2eH4n"}],"key":"nHeL2L36Hn"},{"type":"heading","depth":3,"position":{"start":{"line":295,"column":1},"end":{"line":295,"column":1}},"children":[{"type":"text","value":"Checking out a previous commit","position":{"start":{"line":295,"column":1},"end":{"line":295,"column":1}},"key":"K85nHplx5g"}],"identifier":"checking-out-a-previous-commit","label":"Checking out a previous commit","html_id":"checking-out-a-previous-commit","implicit":true,"key":"SNVuCHeBtO"},{"type":"paragraph","position":{"start":{"line":297,"column":1},"end":{"line":297,"column":1}},"children":[{"type":"text","value":"Let’s say you want to retrieve the file ","position":{"start":{"line":297,"column":1},"end":{"line":297,"column":1}},"key":"cq4Bohz29r"},{"type":"inlineCode","value":"sample.txt","position":{"start":{"line":297,"column":1},"end":{"line":297,"column":1}},"key":"aZkGsPugmL"},{"type":"text","value":" from the previous commit. Two possible reasons why:","position":{"start":{"line":297,"column":1},"end":{"line":297,"column":1}},"key":"SGb1AHVe9s"}],"key":"S8oh3nxO2t"},{"type":"list","ordered":true,"start":1,"spread":false,"position":{"start":{"line":299,"column":1},"end":{"line":301,"column":1}},"children":[{"type":"listItem","spread":true,"position":{"start":{"line":299,"column":1},"end":{"line":299,"column":1}},"children":[{"type":"text","value":"You just want to take a quick look at something in the previous commit, but then go back to the current version. That’s what we’ll do here.","position":{"start":{"line":299,"column":1},"end":{"line":299,"column":1}},"key":"XfrztJWTRI"}],"key":"LWbfB4glzh"},{"type":"listItem","spread":true,"position":{"start":{"line":300,"column":1},"end":{"line":301,"column":1}},"children":[{"type":"text","value":"Maybe you don’t like the most recent commit and want to do some new edits ","position":{"start":{"line":300,"column":1},"end":{"line":300,"column":1}},"key":"KGDfE2BrIb"},{"type":"emphasis","position":{"start":{"line":300,"column":1},"end":{"line":300,"column":1}},"children":[{"type":"text","value":"starting from the previous commit","position":{"start":{"line":300,"column":1},"end":{"line":300,"column":1}},"key":"dowvQFKgDb"}],"key":"ZVVVrOP9qG"},{"type":"text","value":" -- in effect, undoing the most recent commit and going back in time. The simplest way to do this is to ","position":{"start":{"line":300,"column":1},"end":{"line":300,"column":1}},"key":"iEImywLHz5"},{"type":"emphasis","position":{"start":{"line":300,"column":1},"end":{"line":300,"column":1}},"children":[{"type":"text","value":"create a new branch","position":{"start":{"line":300,"column":1},"end":{"line":300,"column":1}},"key":"PAlJjPqYqd"}],"key":"r7LY1koxMp"},{"type":"text","value":" starting from the previous commit. We’ll cover branches more fully in the next lesson.","position":{"start":{"line":300,"column":1},"end":{"line":300,"column":1}},"key":"dKEFQJRw9O"}],"key":"eMRbyNeHQs"}],"key":"RC0U3AgKZf"},{"type":"paragraph","position":{"start":{"line":302,"column":1},"end":{"line":302,"column":1}},"children":[{"type":"text","value":"To retrieve the previous commit, just use ","position":{"start":{"line":302,"column":1},"end":{"line":302,"column":1}},"key":"kFQZ3RCKV4"},{"type":"inlineCode","value":"git checkout","position":{"start":{"line":302,"column":1},"end":{"line":302,"column":1}},"key":"k9V4rNlfBM"},{"type":"text","value":" and the unique number code which you can just copy and paste from the ","position":{"start":{"line":302,"column":1},"end":{"line":302,"column":1}},"key":"nuJuEjOdQ4"},{"type":"inlineCode","value":"git log","position":{"start":{"line":302,"column":1},"end":{"line":302,"column":1}},"key":"jrPHpiYr40"},{"type":"text","value":" output:","position":{"start":{"line":302,"column":1},"end":{"line":302,"column":1}},"key":"G0SEPqwgnl"}],"key":"AJFfDWBqw2"},{"type":"code","lang":"bash","value":"git checkout 35fcbd991f911e170df550db58f74a082ba18b50","position":{"start":{"line":304,"column":1},"end":{"line":306,"column":1}},"key":"ll481lXx8K"},{"type":"paragraph","position":{"start":{"line":308,"column":1},"end":{"line":308,"column":1}},"children":[{"type":"text","value":"You may see output that looks like this:","position":{"start":{"line":308,"column":1},"end":{"line":308,"column":1}},"key":"vw1WRfag1o"}],"key":"DHKY89VsJx"},{"type":"code","lang":"bash","value":"Note: switching to '35fcbd991f911e170df550db58f74a082ba18b50'.\n\nYou are in 'detached HEAD' state. You can look around, make experimental\nchanges and commit them, and you can discard any commits you make in this\nstate without impacting any branches by switching back to a branch.\n\nIf you want to create a new branch to retain commits you create, you may\ndo so (now or later) by using -c with the switch command. Example:\n\n  git switch -c <new-branch-name>\n\nOr undo this operation with:\n\n  git switch -\n\nTurn off this advice by setting config variable advice.detachedHead to false\n\nHEAD is now at 35fcbd9 Close docstring quote on sample.py","position":{"start":{"line":310,"column":1},"end":{"line":329,"column":1}},"key":"SzBQ4r2Qhz"},{"type":"paragraph","position":{"start":{"line":331,"column":1},"end":{"line":331,"column":1}},"children":[{"type":"text","value":"(the details may vary depending on what version of git you are running).","position":{"start":{"line":331,"column":1},"end":{"line":331,"column":1}},"key":"A6vcyMzNkB"}],"key":"DlLm70h4wL"},{"type":"paragraph","position":{"start":{"line":333,"column":1},"end":{"line":333,"column":1}},"children":[{"type":"text","value":"By ","position":{"start":{"line":333,"column":1},"end":{"line":333,"column":1}},"key":"osFHra5Wfj"},{"type":"inlineCode","value":"detached HEAD","position":{"start":{"line":333,"column":1},"end":{"line":333,"column":1}},"key":"uPTXPHMumm"},{"type":"text","value":", git is telling us that we are NOT on the most recent commit in this branch.","position":{"start":{"line":333,"column":1},"end":{"line":333,"column":1}},"key":"OeUl92ptn5"}],"key":"LwiqsBY3gy"},{"type":"paragraph","position":{"start":{"line":335,"column":1},"end":{"line":335,"column":1}},"children":[{"type":"text","value":"If you inspect ","position":{"start":{"line":335,"column":1},"end":{"line":335,"column":1}},"key":"plfLmbYHcd"},{"type":"inlineCode","value":"sample.txt","position":{"start":{"line":335,"column":1},"end":{"line":335,"column":1}},"key":"XspMPOdMUQ"},{"type":"text","value":" in your editor, you will see that the typo ","position":{"start":{"line":335,"column":1},"end":{"line":335,"column":1}},"key":"Ru8wE129Ce"},{"type":"inlineCode","value":"Fxing","position":{"start":{"line":335,"column":1},"end":{"line":335,"column":1}},"key":"jDuGs7xuWu"},{"type":"text","value":" is back!","position":{"start":{"line":335,"column":1},"end":{"line":335,"column":1}},"key":"fqsfdBX3bo"}],"key":"FGfS3CEZNM"},{"type":"paragraph","position":{"start":{"line":337,"column":1},"end":{"line":337,"column":1}},"children":[{"type":"text","value":"As the git message above is reminding us, it’s possible to create an entirely new branch with changes that we make from this point in the history using ","position":{"start":{"line":337,"column":1},"end":{"line":337,"column":1}},"key":"Pubw4zC49O"},{"type":"inlineCode","value":"git switch -c","position":{"start":{"line":337,"column":1},"end":{"line":337,"column":1}},"key":"FKq5Xc8CKj"},{"type":"text","value":". But for now, let’s just go back to the most recent commit on our ","position":{"start":{"line":337,"column":1},"end":{"line":337,"column":1}},"key":"vLv5nKHB4b"},{"type":"inlineCode","value":"fix-typo","position":{"start":{"line":337,"column":1},"end":{"line":337,"column":1}},"key":"OfzFWBogAH"},{"type":"text","value":" branch:","position":{"start":{"line":337,"column":1},"end":{"line":337,"column":1}},"key":"JT5i9030cg"}],"key":"pJIKYP3OWg"},{"type":"code","lang":"bash","value":"git checkout fix-typo","position":{"start":{"line":339,"column":1},"end":{"line":341,"column":1}},"key":"zuQevBlcRD"},{"type":"heading","depth":2,"position":{"start":{"line":343,"column":1},"end":{"line":343,"column":1}},"children":[{"type":"text","value":"Comparing versions","position":{"start":{"line":343,"column":1},"end":{"line":343,"column":1}},"key":"ixYhvKwiMd"}],"identifier":"comparing-versions","label":"Comparing versions","html_id":"comparing-versions","implicit":true,"key":"ugkNE0quUg"},{"type":"paragraph","position":{"start":{"line":345,"column":1},"end":{"line":345,"column":1}},"children":[{"type":"text","value":"We already saw one use of the ","position":{"start":{"line":345,"column":1},"end":{"line":345,"column":1}},"key":"VzpmUcMgy5"},{"type":"inlineCode","value":"git diff","position":{"start":{"line":345,"column":1},"end":{"line":345,"column":1}},"key":"c0ukozpeky"},{"type":"text","value":" command to look at changes in a repo. By default ","position":{"start":{"line":345,"column":1},"end":{"line":345,"column":1}},"key":"bwe3PLqgQN"},{"type":"inlineCode","value":"git diff","position":{"start":{"line":345,"column":1},"end":{"line":345,"column":1}},"key":"XsX1laCVOI"},{"type":"text","value":" will compare the currently saved files against the most recent commit.","position":{"start":{"line":345,"column":1},"end":{"line":345,"column":1}},"key":"eXeOZYwbCF"}],"key":"xEXVrRJSd7"},{"type":"paragraph","position":{"start":{"line":347,"column":1},"end":{"line":347,"column":1}},"children":[{"type":"text","value":"We can also use ","position":{"start":{"line":347,"column":1},"end":{"line":347,"column":1}},"key":"YxfBhpPSBa"},{"type":"inlineCode","value":"git diff","position":{"start":{"line":347,"column":1},"end":{"line":347,"column":1}},"key":"liO7I8XKaf"},{"type":"text","value":" to compare across commits within a branch, or between two different branches. Here are some examples.","position":{"start":{"line":347,"column":1},"end":{"line":347,"column":1}},"key":"TlLu58jxXO"}],"key":"b6xQD44atg"},{"type":"heading","depth":3,"position":{"start":{"line":349,"column":1},"end":{"line":349,"column":1}},"children":[{"type":"text","value":"Compare across commits","position":{"start":{"line":349,"column":1},"end":{"line":349,"column":1}},"key":"z6Ja8LnEAU"}],"identifier":"compare-across-commits","label":"Compare across commits","html_id":"compare-across-commits","implicit":true,"key":"frw5rqzA24"},{"type":"paragraph","position":{"start":{"line":351,"column":1},"end":{"line":351,"column":1}},"children":[{"type":"text","value":"To compare across any commits in our history, we again use the unique commit checksum that we listed with ","position":{"start":{"line":351,"column":1},"end":{"line":351,"column":1}},"key":"mKxOgIS2cu"},{"type":"inlineCode","value":"git log","position":{"start":{"line":351,"column":1},"end":{"line":351,"column":1}},"key":"ETPqjmqAUW"},{"type":"text","value":":","position":{"start":{"line":351,"column":1},"end":{"line":351,"column":1}},"key":"qLvFxVEn1g"}],"key":"YqR3vzqfMi"},{"type":"code","lang":"bash","value":"git diff HEAD 35fcbd991f911e170df550db58f74a082ba18b50","position":{"start":{"line":353,"column":1},"end":{"line":355,"column":1}},"key":"SVqCBAX33C"},{"type":"paragraph","position":{"start":{"line":357,"column":1},"end":{"line":357,"column":1}},"children":[{"type":"text","value":"gives","position":{"start":{"line":357,"column":1},"end":{"line":357,"column":1}},"key":"iyVl3yGO3S"}],"key":"T7MGmirVZM"},{"type":"code","lang":"bash","value":"diff --git a/sample.txt b/sample.txt\nindex edc31c0..4bc074c 100644\n--- a/sample.txt\n+++ b/sample.txt\n@@ -4,6 +4,6 @@ We can use it to demonstrate making pull requests or raising issues in a GitHub\n\n One good way to contribute to a project is to make additions and/or edits to documentation!\n\n-Fixing something as simple as a typo is a great way to get started as a contributor!\n+Fxing something as simple as a typo is a great way to get started as a contributor!\n\n Or, consider adding some more content to this file.","position":{"start":{"line":359,"column":1},"end":{"line":372,"column":1}},"key":"tHgZOM6gSw"},{"type":"admonition","kind":"note","children":[{"type":"admonitionTitle","children":[{"type":"text","value":"Note","key":"XR9dvLcwpy"}],"key":"s82bYd3yF8"},{"type":"paragraph","position":{"start":{"line":375,"column":1},"end":{"line":375,"column":1}},"children":[{"type":"text","value":"Here we use ","position":{"start":{"line":375,"column":1},"end":{"line":375,"column":1}},"key":"gq3m7Ja77z"},{"type":"inlineCode","value":"HEAD","position":{"start":{"line":375,"column":1},"end":{"line":375,"column":1}},"key":"meTHNEKmj9"},{"type":"text","value":" as an alias for the ","position":{"start":{"line":375,"column":1},"end":{"line":375,"column":1}},"key":"gARiIsmILl"},{"type":"emphasis","position":{"start":{"line":375,"column":1},"end":{"line":375,"column":1}},"children":[{"type":"text","value":"most recent commit","position":{"start":{"line":375,"column":1},"end":{"line":375,"column":1}},"key":"Ixf9dv6wVn"}],"key":"XtnzB2CUiD"},{"type":"text","value":".","position":{"start":{"line":375,"column":1},"end":{"line":375,"column":1}},"key":"xkYsJd1pgf"}],"key":"JS26nipUJl"}],"key":"TcqqDQpWUQ"},{"type":"heading","depth":3,"position":{"start":{"line":378,"column":1},"end":{"line":378,"column":1}},"children":[{"type":"text","value":"Compare across branches","position":{"start":{"line":378,"column":1},"end":{"line":378,"column":1}},"key":"M7EVl7E3CR"}],"identifier":"compare-across-branches","label":"Compare across branches","html_id":"compare-across-branches","implicit":true,"key":"LCx2hnUfs0"},{"type":"paragraph","position":{"start":{"line":380,"column":1},"end":{"line":380,"column":1}},"children":[{"type":"text","value":"Recall that, since we have done all our editing in a new branch, the ","position":{"start":{"line":380,"column":1},"end":{"line":380,"column":1}},"key":"zmU7A6VYIA"},{"type":"inlineCode","value":"main","position":{"start":{"line":380,"column":1},"end":{"line":380,"column":1}},"key":"oKTPv87jzb"},{"type":"text","value":" branch still has the typo!","position":{"start":{"line":380,"column":1},"end":{"line":380,"column":1}},"key":"ONuWyhfiRg"}],"key":"gvvrTNSQan"},{"type":"paragraph","position":{"start":{"line":382,"column":1},"end":{"line":382,"column":1}},"children":[{"type":"text","value":"We can see this with ","position":{"start":{"line":382,"column":1},"end":{"line":382,"column":1}},"key":"RkFXwXIbY0"},{"type":"inlineCode","value":"git diff","position":{"start":{"line":382,"column":1},"end":{"line":382,"column":1}},"key":"XBzJKn3gGx"},{"type":"text","value":" using the ","position":{"start":{"line":382,"column":1},"end":{"line":382,"column":1}},"key":"PDiwfJ7yHk"},{"type":"inlineCode","value":"..","position":{"start":{"line":382,"column":1},"end":{"line":382,"column":1}},"key":"Ic9hq0ir6t"},{"type":"text","value":" notation to compare two branches:","position":{"start":{"line":382,"column":1},"end":{"line":382,"column":1}},"key":"EMEfOekLdL"}],"key":"qliiFEmJY1"},{"type":"code","lang":"bash","value":"git diff main..fix-typo","position":{"start":{"line":384,"column":1},"end":{"line":386,"column":1}},"key":"WyI07Myn27"},{"type":"paragraph","position":{"start":{"line":388,"column":1},"end":{"line":388,"column":1}},"children":[{"type":"text","value":"The output is very similar:","position":{"start":{"line":388,"column":1},"end":{"line":388,"column":1}},"key":"QYZdxsr9pX"}],"key":"ZfLZYNX4xR"},{"type":"code","lang":"bash","value":"diff --git a/sample.txt b/sample.txt\nindex 4bc074c..edc31c0 100644\n--- a/sample.txt\n+++ b/sample.txt\n@@ -4,6 +4,6 @@ We can use it to demonstrate making pull requests or raising issues in a GitHub\n\n One good way to contribute to a project is to make additions and/or edits to documentation!\n\n-Fxing something as simple as a typo is a great way to get started as a contributor!\n+Fixing something as simple as a typo is a great way to get started as a contributor!\n\n Or, consider adding some more content to this file.","position":{"start":{"line":390,"column":1},"end":{"line":403,"column":1}},"key":"xXcY2Bhi8o"},{"type":"paragraph","position":{"start":{"line":405,"column":1},"end":{"line":405,"column":1}},"children":[{"type":"text","value":"The ","position":{"start":{"line":405,"column":1},"end":{"line":405,"column":1}},"key":"wRI9U3L6Sd"},{"type":"inlineCode","value":"git diff","position":{"start":{"line":405,"column":1},"end":{"line":405,"column":1}},"key":"Pc1amqD08X"},{"type":"text","value":" command is a powerful comparison tool (and maybe your second new best friend). For many more detail on its usage, see the ","position":{"start":{"line":405,"column":1},"end":{"line":405,"column":1}},"key":"RKvmM6XwVT"},{"type":"link","url":"https://git-scm.com/docs/git-diff","position":{"start":{"line":405,"column":1},"end":{"line":405,"column":1}},"children":[{"type":"text","value":"git documentation","position":{"start":{"line":405,"column":1},"end":{"line":405,"column":1}},"key":"aRSesY4DEs"}],"urlSource":"https://git-scm.com/docs/git-diff","key":"vpi3JTyToE"},{"type":"text","value":".","position":{"start":{"line":405,"column":1},"end":{"line":405,"column":1}},"key":"I5Deai9BwN"}],"key":"q2oQZBbXfO"},{"type":"heading","depth":2,"position":{"start":{"line":407,"column":1},"end":{"line":407,"column":1}},"children":[{"type":"text","value":"Git commands mini-reference","position":{"start":{"line":407,"column":1},"end":{"line":407,"column":1}},"key":"k7Mj89Z8OF"}],"identifier":"git-commands-mini-reference","label":"Git commands mini-reference","html_id":"git-commands-mini-reference","implicit":true,"key":"lIaQYM2wMr"},{"type":"heading","depth":3,"position":{"start":{"line":409,"column":1},"end":{"line":409,"column":1}},"children":[{"type":"text","value":"Commands we used in this tutorial","position":{"start":{"line":409,"column":1},"end":{"line":409,"column":1}},"key":"uC5sXPidCh"}],"identifier":"commands-we-used-in-this-tutorial","label":"Commands we used in this tutorial","html_id":"commands-we-used-in-this-tutorial","implicit":true,"key":"oQWlXzqwgV"},{"type":"list","ordered":false,"spread":false,"position":{"start":{"line":411,"column":1},"end":{"line":413,"column":1}},"children":[{"type":"listItem","spread":true,"position":{"start":{"line":411,"column":1},"end":{"line":411,"column":1}},"children":[{"type":"inlineCode","value":"git status","position":{"start":{"line":411,"column":1},"end":{"line":411,"column":1}},"key":"Yxq9CMzBgv"},{"type":"text","value":": see what branch we’re on and what state our repo is in.","position":{"start":{"line":411,"column":1},"end":{"line":411,"column":1}},"key":"ErVwDrphed"}],"key":"yzqmaGmewb"},{"type":"listItem","spread":true,"position":{"start":{"line":412,"column":1},"end":{"line":413,"column":1}},"children":[{"type":"inlineCode","value":"git checkout","position":{"start":{"line":412,"column":1},"end":{"line":412,"column":1}},"key":"WMgy7bNSnN"},{"type":"text","value":": switch between branches (use the ","position":{"start":{"line":412,"column":1},"end":{"line":412,"column":1}},"key":"rF1UqTE6Lc"},{"type":"inlineCode","value":"-b","position":{"start":{"line":412,"column":1},"end":{"line":412,"column":1}},"key":"UrPl06SVp0"},{"type":"text","value":" flag to create a new branch and check it out)","position":{"start":{"line":412,"column":1},"end":{"line":412,"column":1}},"key":"SX2RyYcT2L"}],"key":"GKIBn4ygn9"}],"key":"rfPtXEZRiS"},{"type":"code","lang":"bash","value":"    git checkout -b new-branch-name\n    git checkout <unique-code-of-commit>\n    git checkout branch-name","position":{"start":{"line":414,"column":1},"end":{"line":418,"column":1}},"key":"QQDhyUfStP"},{"type":"list","ordered":false,"spread":false,"position":{"start":{"line":420,"column":1},"end":{"line":421,"column":1}},"children":[{"type":"listItem","spread":true,"position":{"start":{"line":420,"column":1},"end":{"line":421,"column":1}},"children":[{"type":"inlineCode","value":"git diff","position":{"start":{"line":420,"column":1},"end":{"line":420,"column":1}},"key":"GVQzKFJclk"},{"type":"text","value":": compare files between current version and last commit (default), between two commits, or between two branches.","position":{"start":{"line":420,"column":1},"end":{"line":420,"column":1}},"key":"ob1Q3hHvbs"}],"key":"vGV5YtOxy1"}],"key":"G70R1xmNVB"},{"type":"code","lang":"bash","value":"    git diff commit-one commit-two\n    git diff branch-one..branch-two","position":{"start":{"line":422,"column":1},"end":{"line":425,"column":1}},"key":"nBTWyg9FUF"},{"type":"list","ordered":false,"spread":false,"position":{"start":{"line":427,"column":1},"end":{"line":428,"column":1}},"children":[{"type":"listItem","spread":true,"position":{"start":{"line":427,"column":1},"end":{"line":428,"column":1}},"children":[{"type":"inlineCode","value":"git add","position":{"start":{"line":427,"column":1},"end":{"line":427,"column":1}},"key":"ubypdPVtr7"},{"type":"text","value":": stage a file for a commit.","position":{"start":{"line":427,"column":1},"end":{"line":427,"column":1}},"key":"X58BroHO4J"}],"key":"h1bN37BJ4g"}],"key":"OjZPo5OCnM"},{"type":"code","lang":"bash","value":"    git add file-name","position":{"start":{"line":429,"column":1},"end":{"line":431,"column":1}},"key":"P9uBLqPFJt"},{"type":"list","ordered":false,"spread":false,"position":{"start":{"line":433,"column":1},"end":{"line":434,"column":1}},"children":[{"type":"listItem","spread":true,"position":{"start":{"line":433,"column":1},"end":{"line":434,"column":1}},"children":[{"type":"inlineCode","value":"git commit","position":{"start":{"line":433,"column":1},"end":{"line":433,"column":1}},"key":"ehN8jn8Rdm"},{"type":"text","value":": create a new commit with the staged files.","position":{"start":{"line":433,"column":1},"end":{"line":433,"column":1}},"key":"m63RYZ9G8v"}],"key":"vbM8z3kJi4"}],"key":"K19v0aq6d2"},{"type":"code","lang":"bash","value":"    git commit -m 'message/comment between quotation marks'","position":{"start":{"line":435,"column":1},"end":{"line":437,"column":1}},"key":"jY8n0YbXZV"},{"type":"list","ordered":false,"spread":false,"position":{"start":{"line":439,"column":1},"end":{"line":441,"column":1}},"children":[{"type":"listItem","spread":true,"position":{"start":{"line":439,"column":1},"end":{"line":441,"column":1}},"children":[{"type":"inlineCode","value":"git log","position":{"start":{"line":439,"column":1},"end":{"line":439,"column":1}},"key":"nCcGdX7C0G"},{"type":"text","value":": see the commit history of our branch.","position":{"start":{"line":439,"column":1},"end":{"line":439,"column":1}},"key":"gKRiCfZnmW"},{"type":"list","ordered":false,"spread":false,"position":{"start":{"line":440,"column":1},"end":{"line":441,"column":1}},"children":[{"type":"listItem","spread":true,"position":{"start":{"line":440,"column":1},"end":{"line":441,"column":1}},"children":[{"type":"text","value":"Press ","position":{"start":{"line":440,"column":1},"end":{"line":440,"column":1}},"key":"AIHSyZiqep"},{"type":"inlineCode","value":"Q","position":{"start":{"line":440,"column":1},"end":{"line":440,"column":1}},"key":"Gh3nufR8fb"},{"type":"text","value":" to exit","position":{"start":{"line":440,"column":1},"end":{"line":440,"column":1}},"key":"QUPtxkzhms"}],"key":"FWnrsoO35N"}],"key":"gujWlbzDQ8"}],"key":"eBwK4mA2dn"}],"key":"r1cfrZxpB3"},{"type":"heading","depth":3,"position":{"start":{"line":442,"column":1},"end":{"line":442,"column":1}},"children":[{"type":"text","value":"Some other git commands you’ll want to know","position":{"start":{"line":442,"column":1},"end":{"line":442,"column":1}},"key":"wyEwaZ6OOO"}],"identifier":"some-other-git-commands-youll-want-to-know","label":"Some other git commands you’ll want to know","html_id":"some-other-git-commands-youll-want-to-know","implicit":true,"key":"tyks7zKRo0"},{"type":"paragraph","position":{"start":{"line":444,"column":1},"end":{"line":444,"column":1}},"children":[{"type":"text","value":"We’ll cover many of these in subsequent sections.","position":{"start":{"line":444,"column":1},"end":{"line":444,"column":1}},"key":"lmr31R0qNb"}],"key":"UfbcwjJBtj"},{"type":"list","ordered":false,"spread":false,"position":{"start":{"line":446,"column":1},"end":{"line":451,"column":1}},"children":[{"type":"listItem","spread":true,"position":{"start":{"line":446,"column":1},"end":{"line":446,"column":1}},"children":[{"type":"inlineCode","value":"git branch","position":{"start":{"line":446,"column":1},"end":{"line":446,"column":1}},"key":"N8obUHLour"},{"type":"text","value":": list all the branch in the repo","position":{"start":{"line":446,"column":1},"end":{"line":446,"column":1}},"key":"ekbHfAoU2W"}],"key":"LfoesBHQep"},{"type":"listItem","spread":true,"position":{"start":{"line":447,"column":1},"end":{"line":447,"column":1}},"children":[{"type":"inlineCode","value":"git mv","position":{"start":{"line":447,"column":1},"end":{"line":447,"column":1}},"key":"kcfD9S7T91"},{"type":"text","value":" and ","position":{"start":{"line":447,"column":1},"end":{"line":447,"column":1}},"key":"QdZeD6SSrg"},{"type":"inlineCode","value":"git rm","position":{"start":{"line":447,"column":1},"end":{"line":447,"column":1}},"key":"Ca82apk2Se"},{"type":"text","value":": git-enhanced versions of the ","position":{"start":{"line":447,"column":1},"end":{"line":447,"column":1}},"key":"Di1H4fpgn6"},{"type":"inlineCode","value":"mv","position":{"start":{"line":447,"column":1},"end":{"line":447,"column":1}},"key":"JmmBV2m8GH"},{"type":"text","value":" (move file) and ","position":{"start":{"line":447,"column":1},"end":{"line":447,"column":1}},"key":"RV9Tq12s4D"},{"type":"inlineCode","value":"rm","position":{"start":{"line":447,"column":1},"end":{"line":447,"column":1}},"key":"aqbyGnEFoz"},{"type":"text","value":" (remove file) commands. These will automatically stage the changes in your current branch.","position":{"start":{"line":447,"column":1},"end":{"line":447,"column":1}},"key":"bxKHkKHF0W"}],"key":"VGpUQlFQdo"},{"type":"listItem","spread":true,"position":{"start":{"line":448,"column":1},"end":{"line":448,"column":1}},"children":[{"type":"inlineCode","value":"git merge","position":{"start":{"line":448,"column":1},"end":{"line":448,"column":1}},"key":"BdSsv5XdNU"},{"type":"text","value":": merge changes from one branch into another.","position":{"start":{"line":448,"column":1},"end":{"line":448,"column":1}},"key":"CRdzDzOFkM"}],"key":"zCBrcOM8KW"},{"type":"listItem","spread":true,"position":{"start":{"line":449,"column":1},"end":{"line":449,"column":1}},"children":[{"type":"inlineCode","value":"git push","position":{"start":{"line":449,"column":1},"end":{"line":449,"column":1}},"key":"S0RGTILANJ"},{"type":"text","value":" and ","position":{"start":{"line":449,"column":1},"end":{"line":449,"column":1}},"key":"cjb5wliZ2O"},{"type":"inlineCode","value":"git pull","position":{"start":{"line":449,"column":1},"end":{"line":449,"column":1}},"key":"HQgYQQEdYk"},{"type":"text","value":": export or input changes between your local branch and a remote repository (e.g. hosted on GitHub).","position":{"start":{"line":449,"column":1},"end":{"line":449,"column":1}},"key":"DbxVjYog4C"}],"key":"kVVDbmSVx0"},{"type":"listItem","spread":true,"position":{"start":{"line":450,"column":1},"end":{"line":451,"column":1}},"children":[{"type":"inlineCode","value":"git init","position":{"start":{"line":450,"column":1},"end":{"line":450,"column":1}},"key":"gJSIXBQ36o"},{"type":"text","value":": create a brand-new repo in the current directory","position":{"start":{"line":450,"column":1},"end":{"line":450,"column":1}},"key":"KdmFouFufk"}],"key":"BdlOvGEsol"}],"key":"pcbqwS7dcT"},{"type":"thematicBreak","position":{"start":{"line":452,"column":1},"end":{"line":452,"column":1}},"key":"a8pn8Io4Yl"},{"type":"heading","depth":2,"position":{"start":{"line":454,"column":1},"end":{"line":454,"column":1}},"children":[{"type":"text","value":"Summary","position":{"start":{"line":454,"column":1},"end":{"line":454,"column":1}},"key":"UnOC6V40q4"}],"identifier":"summary","label":"Summary","html_id":"summary","implicit":true,"key":"h0HT2RuyoN"},{"type":"list","ordered":false,"spread":false,"position":{"start":{"line":456,"column":1},"end":{"line":463,"column":1}},"children":[{"type":"listItem","spread":true,"position":{"start":{"line":456,"column":1},"end":{"line":456,"column":1}},"children":[{"type":"text","value":"Version control is an important tool for working with code files (or anything that is saved as plain text).","position":{"start":{"line":456,"column":1},"end":{"line":456,"column":1}},"key":"UTCHnYnQxW"}],"key":"POUAfbn4HS"},{"type":"listItem","spread":true,"position":{"start":{"line":457,"column":1},"end":{"line":457,"column":1}},"children":[{"type":"text","value":"git is the most common version control software in use today.","position":{"start":{"line":457,"column":1},"end":{"line":457,"column":1}},"key":"Y5kbr1rioL"}],"key":"D5e5mvMRE8"},{"type":"listItem","spread":true,"position":{"start":{"line":458,"column":1},"end":{"line":458,"column":1}},"children":[{"type":"inlineCode","value":"git status","position":{"start":{"line":458,"column":1},"end":{"line":458,"column":1}},"key":"fx5EHVUn9c"},{"type":"text","value":" is your new best friend because it gives you a quick view into what’s going on in a git repository.","position":{"start":{"line":458,"column":1},"end":{"line":458,"column":1}},"key":"ELQ2Fx0tOU"}],"key":"UXzLnE2Hpm"},{"type":"listItem","spread":true,"position":{"start":{"line":459,"column":1},"end":{"line":459,"column":1}},"children":[{"type":"text","value":"Every branch of a git repository has a history which is a series of numbered and labelled commits.","position":{"start":{"line":459,"column":1},"end":{"line":459,"column":1}},"key":"ruq63SDDao"}],"key":"OcE9EJ3bkq"},{"type":"listItem","spread":true,"position":{"start":{"line":460,"column":1},"end":{"line":460,"column":1}},"children":[{"type":"text","value":"You can view this history with ","position":{"start":{"line":460,"column":1},"end":{"line":460,"column":1}},"key":"vuNq6awtSn"},{"type":"inlineCode","value":"git log","position":{"start":{"line":460,"column":1},"end":{"line":460,"column":1}},"key":"jGUOwhh1jB"}],"key":"xddLVdRJXZ"},{"type":"listItem","spread":true,"position":{"start":{"line":461,"column":1},"end":{"line":461,"column":1}},"children":[{"type":"text","value":"Making a new commit is a two-step process with ","position":{"start":{"line":461,"column":1},"end":{"line":461,"column":1}},"key":"nnzPZqntNP"},{"type":"inlineCode","value":"git add","position":{"start":{"line":461,"column":1},"end":{"line":461,"column":1}},"key":"iK7TWqJUhM"},{"type":"text","value":" and ","position":{"start":{"line":461,"column":1},"end":{"line":461,"column":1}},"key":"fQkaqNGbWo"},{"type":"inlineCode","value":"git commit","position":{"start":{"line":461,"column":1},"end":{"line":461,"column":1}},"key":"Bcxuk1IIqv"},{"type":"text","value":".","position":{"start":{"line":461,"column":1},"end":{"line":461,"column":1}},"key":"AbPXrFwQ8P"}],"key":"JONqA0YWPA"},{"type":"listItem","spread":true,"position":{"start":{"line":462,"column":1},"end":{"line":463,"column":1}},"children":[{"type":"text","value":"Commits are non-destructive, meaning you can always go back in time to previous commits.","position":{"start":{"line":462,"column":1},"end":{"line":462,"column":1}},"key":"hVPlq6arW1"}],"key":"kWnPaKu3cy"}],"key":"B85adOeueD"},{"type":"heading","depth":3,"position":{"start":{"line":464,"column":1},"end":{"line":464,"column":1}},"children":[{"type":"text","value":"What’s Next?","position":{"start":{"line":464,"column":1},"end":{"line":464,"column":1}},"key":"xNXJg3O1a5"}],"identifier":"whats-next","label":"What’s Next?","html_id":"whats-next","implicit":true,"key":"n6OEKbysgT"},{"type":"paragraph","position":{"start":{"line":466,"column":1},"end":{"line":466,"column":1}},"children":[{"type":"text","value":"Next we’ll explore the concept of branching in git repositories in more detail, including how to merge changes made on one branch into another branch.","position":{"start":{"line":466,"column":1},"end":{"line":466,"column":1}},"key":"XuevVSPfUA"}],"key":"mAGynmTYrf"},{"type":"heading","depth":2,"position":{"start":{"line":468,"column":1},"end":{"line":468,"column":1}},"children":[{"type":"text","value":"References","position":{"start":{"line":468,"column":1},"end":{"line":468,"column":1}},"key":"MPpeSRdUgs"}],"identifier":"references","label":"References","html_id":"references","implicit":true,"key":"MaX5D2gubN"},{"type":"list","ordered":true,"start":1,"spread":false,"position":{"start":{"line":470,"column":1},"end":{"line":471,"column":1}},"children":[{"type":"listItem","spread":true,"position":{"start":{"line":470,"column":1},"end":{"line":470,"column":1}},"children":[{"type":"link","url":"https://git-scm.com/doc","position":{"start":{"line":470,"column":1},"end":{"line":470,"column":1}},"children":[{"type":"text","value":"Official git documentation","position":{"start":{"line":470,"column":1},"end":{"line":470,"column":1}},"key":"quueo79OcK"}],"urlSource":"https://git-scm.com/doc","key":"aYQ9nqAl3E"}],"key":"MPgqNuaiio"},{"type":"listItem","spread":true,"position":{"start":{"line":471,"column":1},"end":{"line":471,"column":1}},"children":[{"type":"link","url":"https://swcarpentry.github.io/git-novice/","position":{"start":{"line":471,"column":1},"end":{"line":471,"column":1}},"children":[{"type":"text","value":"The Software Carpentries beginner lessons on git","position":{"start":{"line":471,"column":1},"end":{"line":471,"column":1}},"key":"a3nmFT6bRc"}],"urlSource":"https://swcarpentry.github.io/git-novice/","key":"eYIGCOAXon"}],"key":"ka6tdbv04Q"}],"key":"t4UCzeMAPK"}],"key":"q6i9UeXKVl"}],"key":"bd3mJXf6hf"},"references":{"cite":{"order":[],"data":{}}},"footer":{"navigation":{"prev":{"title":"Configuring Your GitHub Account","url":"/foundations/github/github-setup-advanced","group":"Foundational skills"},"next":{"title":"Git Branches","url":"/foundations/github/git-branches","group":"Foundational skills"}}},"domain":"http://localhost:3000"}